{
"meta":{"test_sets":[],"test_metrics":[],"learn_metrics":[{"best_value":"Min","name":"RMSE"}],"launch_mode":"Train","parameters":"","iteration_count":1000,"learn_sets":["learn"],"name":"experiment"},
"iterations":[
{"learn":[14.59871775],"iteration":0,"passed_time":0.001200331081,"remaining_time":1.19913075},
{"learn":[14.22518863],"iteration":1,"passed_time":0.002228266716,"remaining_time":1.111905091},
{"learn":[13.8866124],"iteration":2,"passed_time":0.003260203059,"remaining_time":1.08347415},
{"learn":[13.52356875],"iteration":3,"passed_time":0.00426649314,"remaining_time":1.062356792},
{"learn":[13.18870211],"iteration":4,"passed_time":0.005560525321,"remaining_time":1.106544539},
{"learn":[12.9124226],"iteration":5,"passed_time":0.006633542479,"remaining_time":1.098956871},
{"learn":[12.60003351],"iteration":6,"passed_time":0.007694916649,"remaining_time":1.09157889},
{"learn":[12.32990573],"iteration":7,"passed_time":0.008759259529,"remaining_time":1.086148182},
{"learn":[12.0660619],"iteration":8,"passed_time":0.00971936426,"remaining_time":1.070209998},
{"learn":[11.77309809],"iteration":9,"passed_time":0.01486192822,"remaining_time":1.471330894},
{"learn":[11.49227636],"iteration":10,"passed_time":0.01595227651,"remaining_time":1.434254679},
{"learn":[11.26264833],"iteration":11,"passed_time":0.01723641967,"remaining_time":1.419131887},
{"learn":[11.04260393],"iteration":12,"passed_time":0.01836362783,"remaining_time":1.394223128},
{"learn":[10.79916926],"iteration":13,"passed_time":0.01935712092,"remaining_time":1.363294373},
{"learn":[10.5541002],"iteration":14,"passed_time":0.02028802074,"remaining_time":1.332246695},
{"learn":[10.31918115],"iteration":15,"passed_time":0.02122276176,"remaining_time":1.305199848},
{"learn":[10.10004441],"iteration":16,"passed_time":0.02216049104,"remaining_time":1.281397806},
{"learn":[9.894556723],"iteration":17,"passed_time":0.0230852464,"remaining_time":1.259428443},
{"learn":[9.690174082],"iteration":18,"passed_time":0.02398170421,"remaining_time":1.238213254},
{"learn":[9.506034866],"iteration":19,"passed_time":0.02499581772,"remaining_time":1.224795068},
{"learn":[9.338524633],"iteration":20,"passed_time":0.02962984638,"remaining_time":1.381315219},
{"learn":[9.170203312],"iteration":21,"passed_time":0.03067286482,"remaining_time":1.363548263},
{"learn":[9.010299969],"iteration":22,"passed_time":0.03175024077,"remaining_time":1.34869501},
{"learn":[8.843866678],"iteration":23,"passed_time":0.03264971693,"remaining_time":1.327755155},
{"learn":[8.690548059],"iteration":24,"passed_time":0.03370581862,"remaining_time":1.314526926},
{"learn":[8.555307687],"iteration":25,"passed_time":0.03458523525,"remaining_time":1.29561612},
{"learn":[8.413851302],"iteration":26,"passed_time":0.03554586232,"remaining_time":1.280967557},
{"learn":[8.29256019],"iteration":27,"passed_time":0.03650272264,"remaining_time":1.267165943},
{"learn":[8.162193833],"iteration":28,"passed_time":0.03744838046,"remaining_time":1.253875084},
{"learn":[8.040736294],"iteration":29,"passed_time":0.03845584619,"remaining_time":1.243405694},
{"learn":[7.921220278],"iteration":30,"passed_time":0.03945286255,"remaining_time":1.233220123},
{"learn":[7.809589039],"iteration":31,"passed_time":0.04037993225,"remaining_time":1.221492951},
{"learn":[7.699675801],"iteration":32,"passed_time":0.04249325476,"remaining_time":1.245181132},
{"learn":[7.60645267],"iteration":33,"passed_time":0.04561085353,"remaining_time":1.295884838},
{"learn":[7.498880302],"iteration":34,"passed_time":0.04649716986,"remaining_time":1.281993398},
{"learn":[7.401158744],"iteration":35,"passed_time":0.04753154255,"remaining_time":1.272789084},
{"learn":[7.306431077],"iteration":36,"passed_time":0.04913870958,"remaining_time":1.278934522},
{"learn":[7.223863468],"iteration":37,"passed_time":0.05008219724,"remaining_time":1.267870362},
{"learn":[7.143477682],"iteration":38,"passed_time":0.05122224199,"remaining_time":1.262168578},
{"learn":[7.062817131],"iteration":39,"passed_time":0.05223320089,"remaining_time":1.253596821},
{"learn":[6.990793435],"iteration":40,"passed_time":0.05319822953,"remaining_time":1.244319564},
{"learn":[6.931862224],"iteration":41,"passed_time":0.05420727548,"remaining_time":1.236442141},
{"learn":[6.858296558],"iteration":42,"passed_time":0.05582577864,"remaining_time":1.242448143},
{"learn":[6.786268161],"iteration":43,"passed_time":0.05755321835,"remaining_time":1.250474472},
{"learn":[6.717118549],"iteration":44,"passed_time":0.05878022823,"remaining_time":1.247447066},
{"learn":[6.652948106],"iteration":45,"passed_time":0.06253798906,"remaining_time":1.296983512},
{"learn":[6.589686076],"iteration":46,"passed_time":0.06343728354,"remaining_time":1.286292154},
{"learn":[6.531283097],"iteration":47,"passed_time":0.0643912285,"remaining_time":1.277092699},
{"learn":[6.471368031],"iteration":48,"passed_time":0.06540715145,"remaining_time":1.269432674},
{"learn":[6.416481395],"iteration":49,"passed_time":0.06625714134,"remaining_time":1.258885685},
{"learn":[6.369870822],"iteration":50,"passed_time":0.06713888234,"remaining_time":1.249309791},
{"learn":[6.325678067],"iteration":51,"passed_time":0.0679871526,"remaining_time":1.23945809},
{"learn":[6.275766122],"iteration":52,"passed_time":0.06885771908,"remaining_time":1.230344528},
{"learn":[6.224773967],"iteration":53,"passed_time":0.06976679641,"remaining_time":1.222210915},
{"learn":[6.182249254],"iteration":54,"passed_time":0.07145198863,"remaining_time":1.227675077},
{"learn":[6.139904173],"iteration":55,"passed_time":0.07334257331,"remaining_time":1.236346236},
{"learn":[6.100525536],"iteration":56,"passed_time":0.0746455676,"remaining_time":1.234925794},
{"learn":[6.062568564],"iteration":57,"passed_time":0.07585556641,"remaining_time":1.231999027},
{"learn":[6.030559288],"iteration":58,"passed_time":0.07685408428,"remaining_time":1.225757514},
{"learn":[5.997931376],"iteration":59,"passed_time":0.07778163777,"remaining_time":1.218578992},
{"learn":[5.964103835],"iteration":60,"passed_time":0.07885025546,"remaining_time":1.213776883},
{"learn":[5.933729724],"iteration":61,"passed_time":0.07998048989,"remaining_time":1.210027412},
{"learn":[5.901932711],"iteration":62,"passed_time":0.08104044176,"remaining_time":1.205315777},
{"learn":[5.873727795],"iteration":63,"passed_time":0.08205674603,"remaining_time":1.200079911},
{"learn":[5.846485734],"iteration":64,"passed_time":0.08308367819,"remaining_time":1.195126755},
{"learn":[5.820630862],"iteration":65,"passed_time":0.08407941379,"remaining_time":1.189851098},
{"learn":[5.793646238],"iteration":66,"passed_time":0.08523159534,"remaining_time":1.186881768},
{"learn":[5.765388646],"iteration":67,"passed_time":0.08689387816,"remaining_time":1.190957271},
{"learn":[5.747073912],"iteration":68,"passed_time":0.0881810719,"remaining_time":1.189805477},
{"learn":[5.722315217],"iteration":69,"passed_time":0.08915642105,"remaining_time":1.184506737},
{"learn":[5.699970599],"iteration":70,"passed_time":0.09006392345,"remaining_time":1.178442041},
{"learn":[5.682732647],"iteration":71,"passed_time":0.09096171324,"remaining_time":1.172395415},
{"learn":[5.663525791],"iteration":72,"passed_time":0.09191918041,"remaining_time":1.167247674},
{"learn":[5.642381613],"iteration":73,"passed_time":0.0928066687,"remaining_time":1.161337503},
{"learn":[5.621404779],"iteration":74,"passed_time":0.09369489957,"remaining_time":1.155570428},
{"learn":[5.602460129],"iteration":75,"passed_time":0.09466359988,"remaining_time":1.150910083},
{"learn":[5.587337574],"iteration":76,"passed_time":0.09560826531,"remaining_time":1.146057518},
{"learn":[5.572393026],"iteration":77,"passed_time":0.09661711743,"remaining_time":1.142063875},
{"learn":[5.558425806],"iteration":78,"passed_time":0.09759917985,"remaining_time":1.137833476},
{"learn":[5.541518902],"iteration":79,"passed_time":0.09856139716,"remaining_time":1.133456067},
{"learn":[5.526157283],"iteration":80,"passed_time":0.0995903104,"remaining_time":1.129919694},
{"learn":[5.511746977],"iteration":81,"passed_time":0.1010261758,"remaining_time":1.131000358},
{"learn":[5.504975022],"iteration":82,"passed_time":0.1018627428,"remaining_time":1.125399219},
{"learn":[5.493980522],"iteration":83,"passed_time":0.1028921536,"remaining_time":1.122014437},
{"learn":[5.480745463],"iteration":84,"passed_time":0.103802884,"remaining_time":1.117407516},
{"learn":[5.464052013],"iteration":85,"passed_time":0.1048308793,"remaining_time":1.114132834},
{"learn":[5.449143727],"iteration":86,"passed_time":0.1057018097,"remaining_time":1.10926152},
{"learn":[5.438255432],"iteration":87,"passed_time":0.1068465745,"remaining_time":1.107319045},
{"learn":[5.425927931],"iteration":88,"passed_time":0.1078939047,"remaining_time":1.10439716},
{"learn":[5.412331217],"iteration":89,"passed_time":0.1088327922,"remaining_time":1.100420455},
{"learn":[5.400691499],"iteration":90,"passed_time":0.1097228938,"remaining_time":1.096023192},
{"learn":[5.391618744],"iteration":91,"passed_time":0.1106751999,"remaining_time":1.092316103},
{"learn":[5.380766572],"iteration":92,"passed_time":0.1115899654,"remaining_time":1.088302135},
{"learn":[5.372207183],"iteration":93,"passed_time":0.1125104898,"remaining_time":1.084409614},
{"learn":[5.362918837],"iteration":94,"passed_time":0.1135288512,"remaining_time":1.081511687},
{"learn":[5.348292324],"iteration":95,"passed_time":0.1158667304,"remaining_time":1.091078378},
{"learn":[5.339772295],"iteration":96,"passed_time":0.1169748825,"remaining_time":1.088951742},
{"learn":[5.331515983],"iteration":97,"passed_time":0.1179745333,"remaining_time":1.085847235},
{"learn":[5.323861644],"iteration":98,"passed_time":0.1188900096,"remaining_time":1.082019179},
{"learn":[5.313277281],"iteration":99,"passed_time":0.119813958,"remaining_time":1.078325622},
{"learn":[5.30685627],"iteration":100,"passed_time":0.1206500576,"remaining_time":1.073904969},
{"learn":[5.29652059],"iteration":101,"passed_time":0.121588333,"remaining_time":1.070454148},
{"learn":[5.288350766],"iteration":102,"passed_time":0.1225866602,"remaining_time":1.06757509},
{"learn":[5.27993346],"iteration":103,"passed_time":0.1236341019,"remaining_time":1.06515534},
{"learn":[5.271789139],"iteration":104,"passed_time":0.1247527995,"remaining_time":1.063369101},
{"learn":[5.262684686],"iteration":105,"passed_time":0.1257042648,"remaining_time":1.060185026},
{"learn":[5.251619772],"iteration":106,"passed_time":0.1266200105,"remaining_time":1.056744574},
{"learn":[5.241012171],"iteration":107,"passed_time":0.1275431772,"remaining_time":1.053412168},
{"learn":[5.232684032],"iteration":108,"passed_time":0.1284301442,"remaining_time":1.04982806},
{"learn":[5.224267141],"iteration":109,"passed_time":0.1306419898,"remaining_time":1.057012463},
{"learn":[5.216324968],"iteration":110,"passed_time":0.1326873124,"remaining_time":1.062693881},
{"learn":[5.211102527],"iteration":111,"passed_time":0.1336613766,"remaining_time":1.059743772},
{"learn":[5.206364257],"iteration":112,"passed_time":0.1345735795,"remaining_time":1.056343053},
{"learn":[5.196937641],"iteration":113,"passed_time":0.135376014,"remaining_time":1.052132881},
{"learn":[5.190746047],"iteration":114,"passed_time":0.1361952188,"remaining_time":1.048111032},
{"learn":[5.181885213],"iteration":115,"passed_time":0.1371179936,"remaining_time":1.044933676},
{"learn":[5.178293568],"iteration":116,"passed_time":0.1378309628,"remaining_time":1.040211454},
{"learn":[5.170991438],"iteration":117,"passed_time":0.1387473655,"remaining_time":1.037077766},
{"learn":[5.166257212],"iteration":118,"passed_time":0.1397287435,"remaining_time":1.034462378},
{"learn":[5.161421246],"iteration":119,"passed_time":0.1406959428,"remaining_time":1.031770247},
{"learn":[5.158223542],"iteration":120,"passed_time":0.1417573259,"remaining_time":1.029790822},
{"learn":[5.15470988],"iteration":121,"passed_time":0.1425733502,"remaining_time":1.026060668},
{"learn":[5.146388143],"iteration":122,"passed_time":0.1435490194,"remaining_time":1.023516179},
{"learn":[5.139529364],"iteration":123,"passed_time":0.1450664966,"remaining_time":1.024824605},
{"learn":[5.134276023],"iteration":124,"passed_time":0.1462419399,"remaining_time":1.023693579},
{"learn":[5.128536065],"iteration":125,"passed_time":0.1472225541,"remaining_time":1.021210415},
{"learn":[5.123300353],"iteration":126,"passed_time":0.148016421,"remaining_time":1.017467209},
{"learn":[5.116200518],"iteration":127,"passed_time":0.1490898945,"remaining_time":1.015674906},
{"learn":[5.108728704],"iteration":128,"passed_time":0.1509096775,"remaining_time":1.018932783},
{"learn":[5.104075866],"iteration":129,"passed_time":0.1519575084,"remaining_time":1.016946402},
{"learn":[5.100317606],"iteration":130,"passed_time":0.1530293684,"remaining_time":1.015133749},
{"learn":[5.095814182],"iteration":131,"passed_time":0.1540127232,"remaining_time":1.012750331},
{"learn":[5.092146915],"iteration":132,"passed_time":0.1550200331,"remaining_time":1.010544125},
{"learn":[5.085258329],"iteration":133,"passed_time":0.1559331212,"remaining_time":1.007746888},
{"learn":[5.079219421],"iteration":134,"passed_time":0.1569303879,"remaining_time":1.00551693},
{"learn":[5.076476829],"iteration":135,"passed_time":0.1581418792,"remaining_time":1.004666056},
{"learn":[5.072133867],"iteration":136,"passed_time":0.1598827148,"remaining_time":1.007144401},
{"learn":[5.067031564],"iteration":137,"passed_time":0.1609738321,"remaining_time":1.005503212},
{"learn":[5.061358312],"iteration":138,"passed_time":0.1624428012,"remaining_time":1.006210445},
{"learn":[5.056759124],"iteration":139,"passed_time":0.1633330812,"remaining_time":1.003331785},
{"learn":[5.050254],"iteration":140,"passed_time":0.1642547475,"remaining_time":1.00067254},
{"learn":[5.048376474],"iteration":141,"passed_time":0.1649412681,"remaining_time":0.9966169581},
{"learn":[5.042603751],"iteration":142,"passed_time":0.1658749502,"remaining_time":0.9940897366},
{"learn":[5.037477349],"iteration":143,"passed_time":0.1668642049,"remaining_time":0.991914996},
{"learn":[5.03230489],"iteration":144,"passed_time":0.1680151316,"remaining_time":0.990709914},
{"learn":[5.025976187],"iteration":145,"passed_time":0.1691437663,"remaining_time":0.9893751808},
{"learn":[5.01952451],"iteration":146,"passed_time":0.1701092528,"remaining_time":0.9870965487},
{"learn":[5.017569424],"iteration":147,"passed_time":0.1711568313,"remaining_time":0.9853082449},
{"learn":[5.008962367],"iteration":148,"passed_time":0.1721823966,"remaining_time":0.9834041577},
{"learn":[5.003880266],"iteration":149,"passed_time":0.1747874921,"remaining_time":0.9904624552},
{"learn":[4.996387564],"iteration":150,"passed_time":0.1761585629,"remaining_time":0.9904544363},
{"learn":[4.993361683],"iteration":151,"passed_time":0.1775291863,"remaining_time":0.9904259869},
{"learn":[4.99005752],"iteration":152,"passed_time":0.1784864924,"remaining_time":0.9880918894},
{"learn":[4.986908764],"iteration":153,"passed_time":0.1794070311,"remaining_time":0.9855736901},
{"learn":[4.985207175],"iteration":154,"passed_time":0.1803931729,"remaining_time":0.9834337489},
{"learn":[4.979003494],"iteration":155,"passed_time":0.1814112485,"remaining_time":0.9814813704},
{"learn":[4.973142217],"iteration":156,"passed_time":0.1825115888,"remaining_time":0.9799826076},
{"learn":[4.967056696],"iteration":157,"passed_time":0.1835006592,"remaining_time":0.9778959182},
{"learn":[4.961460696],"iteration":158,"passed_time":0.1846187801,"remaining_time":0.976505623},
{"learn":[4.954240363],"iteration":159,"passed_time":0.1856849335,"remaining_time":0.9748459007},
{"learn":[4.952320707],"iteration":160,"passed_time":0.1863079735,"remaining_time":0.9708844087},
{"learn":[4.948337777],"iteration":161,"passed_time":0.1872420037,"remaining_time":0.9685728339},
{"learn":[4.943228639],"iteration":162,"passed_time":0.188834559,"remaining_time":0.9696596681},
{"learn":[4.938545759],"iteration":163,"passed_time":0.1903064487,"remaining_time":0.9700987265},
{"learn":[4.935330572],"iteration":164,"passed_time":0.1914191213,"remaining_time":0.9686967651},
{"learn":[4.932051543],"iteration":165,"passed_time":0.1923792677,"remaining_time":0.9665319835},
{"learn":[4.928964153],"iteration":166,"passed_time":0.1933290546,"remaining_time":0.9643299548},
{"learn":[4.922860227],"iteration":167,"passed_time":0.194283665,"remaining_time":0.9621667219},
{"learn":[4.917668772],"iteration":168,"passed_time":0.1953652909,"remaining_time":0.9606423477},
{"learn":[4.910365386],"iteration":169,"passed_time":0.1966442176,"remaining_time":0.9600864742},
{"learn":[4.906457206],"iteration":170,"passed_time":0.1977290864,"remaining_time":0.9585813602},
{"learn":[4.901996508],"iteration":171,"passed_time":0.1988348755,"remaining_time":0.9571818427},
{"learn":[4.896816173],"iteration":172,"passed_time":0.1998569424,"remaining_time":0.9553854993},
{"learn":[4.891123132],"iteration":173,"passed_time":0.2008161662,"remaining_time":0.9532997315},
{"learn":[4.887630202],"iteration":174,"passed_time":0.2020875124,"remaining_time":0.9526982726},
{"learn":[4.885259712],"iteration":175,"passed_time":0.2037666003,"remaining_time":0.953998174},
{"learn":[4.880659728],"iteration":176,"passed_time":0.2052424601,"remaining_time":0.9543194612},
{"learn":[4.877299723],"iteration":177,"passed_time":0.2062884071,"remaining_time":0.9526352282},
{"learn":[4.874038772],"iteration":178,"passed_time":0.2072459788,"remaining_time":0.9505527856},
{"learn":[4.86943698],"iteration":179,"passed_time":0.2082610134,"remaining_time":0.9487446167},
{"learn":[4.861268711],"iteration":180,"passed_time":0.2092677271,"remaining_time":0.9469075606},
{"learn":[4.858673056],"iteration":181,"passed_time":0.210306289,"remaining_time":0.9452227715},
{"learn":[4.854036207],"iteration":182,"passed_time":0.2114621829,"remaining_time":0.9440688713},
{"learn":[4.85130244],"iteration":183,"passed_time":0.212739035,"remaining_time":0.9434513727},
{"learn":[4.847510084],"iteration":184,"passed_time":0.2136431747,"remaining_time":0.9411847967},
{"learn":[4.845691673],"iteration":185,"passed_time":0.2146734321,"remaining_time":0.9394848049},
{"learn":[4.842058646],"iteration":186,"passed_time":0.2173718516,"remaining_time":0.9450444671},
{"learn":[4.838623675],"iteration":187,"passed_time":0.2187333994,"remaining_time":0.9447421292},
{"learn":[4.834602161],"iteration":188,"passed_time":0.2205212009,"remaining_time":0.94625764},
{"learn":[4.830858976],"iteration":189,"passed_time":0.2219410735,"remaining_time":0.9461698397},
{"learn":[4.827590511],"iteration":190,"passed_time":0.223251718,"remaining_time":0.9456054443},
{"learn":[4.822246226],"iteration":191,"passed_time":0.2244648762,"remaining_time":0.9446230206},
{"learn":[4.816686395],"iteration":192,"passed_time":0.2254595703,"remaining_time":0.9427247317},
{"learn":[4.814797121],"iteration":193,"passed_time":0.2264031894,"remaining_time":0.9406235603},
{"learn":[4.811639392],"iteration":194,"passed_time":0.2274339681,"remaining_time":0.9388940734},
{"learn":[4.804813432],"iteration":195,"passed_time":0.2285877304,"remaining_time":0.9376762002},
{"learn":[4.80251613],"iteration":196,"passed_time":0.2297582539,"remaining_time":0.9365272991},
{"learn":[4.800087884],"iteration":197,"passed_time":0.2307964895,"remaining_time":0.9348423463},
{"learn":[4.794773135],"iteration":198,"passed_time":0.2323415217,"remaining_time":0.9352038134},
{"learn":[4.791664833],"iteration":199,"passed_time":0.2336544203,"remaining_time":0.9346176812},
{"learn":[4.785989873],"iteration":200,"passed_time":0.2354991302,"remaining_time":0.9361383334},
{"learn":[4.782387142],"iteration":201,"passed_time":0.2369101737,"remaining_time":0.9359124685},
{"learn":[4.778623704],"iteration":202,"passed_time":0.238016583,"remaining_time":0.9344788996},
{"learn":[4.775772178],"iteration":203,"passed_time":0.2391106283,"remaining_time":0.9330002946},
{"learn":[4.77023101],"iteration":204,"passed_time":0.2401223387,"remaining_time":0.9312061428},
{"learn":[4.764496689],"iteration":205,"passed_time":0.2410954559,"remaining_time":0.9292708349},
{"learn":[4.763138716],"iteration":206,"passed_time":0.2419984178,"remaining_time":0.9270760645},
{"learn":[4.758053283],"iteration":207,"passed_time":0.2431432719,"remaining_time":0.925814766},
{"learn":[4.755063788],"iteration":208,"passed_time":0.2448201411,"remaining_time":0.9265680936},
{"learn":[4.752465267],"iteration":209,"passed_time":0.2462815291,"remaining_time":0.9264876571},
{"learn":[4.748067377],"iteration":210,"passed_time":0.2484994151,"remaining_time":0.9292229314},
{"learn":[4.744163298],"iteration":211,"passed_time":0.249804569,"remaining_time":0.9285188697},
{"learn":[4.736670896],"iteration":212,"passed_time":0.2512757785,"remaining_time":0.928422712},
{"learn":[4.73349255],"iteration":213,"passed_time":0.2529070839,"remaining_time":0.9289017194},
{"learn":[4.731864595],"iteration":214,"passed_time":0.2542227236,"remaining_time":0.928208549},
{"learn":[4.728398311],"iteration":215,"passed_time":0.2555591443,"remaining_time":0.9275850422},
{"learn":[4.723865975],"iteration":216,"passed_time":0.2567422953,"remaining_time":0.9264019227},
{"learn":[4.723483365],"iteration":217,"passed_time":0.2577943498,"remaining_time":0.9247485392},
{"learn":[4.72095416],"iteration":218,"passed_time":0.2593733867,"remaining_time":0.9249799772},
{"learn":[4.716173382],"iteration":219,"passed_time":0.2619470622,"remaining_time":0.9287214025},
{"learn":[4.710563974],"iteration":220,"passed_time":0.2635079805,"remaining_time":0.9288358228},
{"learn":[4.707160263],"iteration":221,"passed_time":0.265474894,"remaining_time":0.9303579618},
{"learn":[4.70408351],"iteration":222,"passed_time":0.2665703965,"remaining_time":0.9288125473},
{"learn":[4.702501831],"iteration":223,"passed_time":0.2689406891,"remaining_time":0.9316873874},
{"learn":[4.700269738],"iteration":224,"passed_time":0.2704599568,"remaining_time":0.9315842955},
{"learn":[4.695346302],"iteration":225,"passed_time":0.2717435665,"remaining_time":0.930661595},
{"learn":[4.689769299],"iteration":226,"passed_time":0.2730383671,"remaining_time":0.9297738229},
{"learn":[4.687919514],"iteration":227,"passed_time":0.2742430871,"remaining_time":0.9285774704},
{"learn":[4.682982074],"iteration":228,"passed_time":0.2784729628,"remaining_time":0.9375661761},
{"learn":[4.679578702],"iteration":229,"passed_time":0.2818673732,"remaining_time":0.9436429449},
{"learn":[4.675751423],"iteration":230,"passed_time":0.2846337936,"remaining_time":0.9475471312},
{"learn":[4.672710726],"iteration":231,"passed_time":0.2857062668,"remaining_time":0.9457862625},
{"learn":[4.6690533],"iteration":232,"passed_time":0.2867223735,"remaining_time":0.9438457532},
{"learn":[4.667595702],"iteration":233,"passed_time":0.2891751527,"remaining_time":0.946616098},
{"learn":[4.664241291],"iteration":234,"passed_time":0.2902665652,"remaining_time":0.9449103079},
{"learn":[4.662246999],"iteration":235,"passed_time":0.2921399016,"remaining_time":0.9457410375},
{"learn":[4.658668443],"iteration":236,"passed_time":0.2936255485,"remaining_time":0.9453008165},
{"learn":[4.658017572],"iteration":237,"passed_time":0.2947583371,"remaining_time":0.9437220707},
{"learn":[4.657656705],"iteration":238,"passed_time":0.2960161204,"remaining_time":0.9425450529},
{"learn":[4.653242871],"iteration":239,"passed_time":0.2972391132,"remaining_time":0.9412571919},
{"learn":[4.6507302],"iteration":240,"passed_time":0.2991488738,"remaining_time":0.9421327603},
{"learn":[4.647671336],"iteration":241,"passed_time":0.3002054635,"remaining_time":0.9403129808},
{"learn":[4.645506007],"iteration":242,"passed_time":0.3010554936,"remaining_time":0.9378560026},
{"learn":[4.641297906],"iteration":243,"passed_time":0.302130767,"remaining_time":0.9361100812},
{"learn":[4.63798107],"iteration":244,"passed_time":0.3032190845,"remaining_time":0.9344098319},
{"learn":[4.635062318],"iteration":245,"passed_time":0.3041613321,"remaining_time":0.9322668471},
{"learn":[4.631606017],"iteration":246,"passed_time":0.3052120636,"remaining_time":0.9304643072},
{"learn":[4.630215494],"iteration":247,"passed_time":0.3070691622,"remaining_time":0.9311129434},
{"learn":[4.62729814],"iteration":248,"passed_time":0.3089996488,"remaining_time":0.9319627963},
{"learn":[4.624691756],"iteration":249,"passed_time":0.3101702131,"remaining_time":0.9305106392},
{"learn":[4.621840053],"iteration":250,"passed_time":0.3116631468,"remaining_time":0.930022697},
{"learn":[4.619602091],"iteration":251,"passed_time":0.3131751598,"remaining_time":0.9295834108},
{"learn":[4.613584029],"iteration":252,"passed_time":0.3141321004,"remaining_time":0.9274967549},
{"learn":[4.6119388],"iteration":253,"passed_time":0.315042084,"remaining_time":0.9252810814},
{"learn":[4.60870702],"iteration":254,"passed_time":0.3160079345,"remaining_time":0.9232388674},
{"learn":[4.604771557],"iteration":255,"passed_time":0.3172514864,"remaining_time":0.9220121324},
{"learn":[4.604231277],"iteration":256,"passed_time":0.3182946057,"remaining_time":0.9202058057},
{"learn":[4.600750354],"iteration":257,"passed_time":0.3193260979,"remaining_time":0.918371956},
{"learn":[4.596488253],"iteration":258,"passed_time":0.3215633405,"remaining_time":0.9199939586},
{"learn":[4.59470784],"iteration":259,"passed_time":0.3230545271,"remaining_time":0.9194628847},
{"learn":[4.588818005],"iteration":260,"passed_time":0.3247896571,"remaining_time":0.9196151594},
{"learn":[4.585054174],"iteration":261,"passed_time":0.3263317893,"remaining_time":0.9192093911},
{"learn":[4.581471435],"iteration":262,"passed_time":0.3275456409,"remaining_time":0.9178750469},
{"learn":[4.577555199],"iteration":263,"passed_time":0.3286353226,"remaining_time":0.916195445},
{"learn":[4.57457145],"iteration":264,"passed_time":0.3296462631,"remaining_time":0.9143018994},
{"learn":[4.573029224],"iteration":265,"passed_time":0.3308287058,"remaining_time":0.9128882334},
{"learn":[4.571326203],"iteration":266,"passed_time":0.3318255368,"remaining_time":0.9109667359},
{"learn":[4.571019224],"iteration":267,"passed_time":0.3327482984,"remaining_time":0.90884983},
{"learn":[4.565766631],"iteration":268,"passed_time":0.3337163623,"remaining_time":0.9068649102},
{"learn":[4.563383471],"iteration":269,"passed_time":0.3378430841,"remaining_time":0.9134275978},
{"learn":[4.558165805],"iteration":270,"passed_time":0.3396477642,"remaining_time":0.9136650188},
{"learn":[4.55629209],"iteration":271,"passed_time":0.3418992181,"remaining_time":0.9150832015},
{"learn":[4.549383848],"iteration":272,"passed_time":0.3428272316,"remaining_time":0.9129501736},
{"learn":[4.546227503],"iteration":273,"passed_time":0.344136344,"remaining_time":0.9118357143},
{"learn":[4.540620977],"iteration":274,"passed_time":0.3450693992,"remaining_time":0.909728416},
{"learn":[4.532898237],"iteration":275,"passed_time":0.3462494024,"remaining_time":0.9082774179},
{"learn":[4.529757367],"iteration":276,"passed_time":0.3473274232,"remaining_time":0.9065621913},
{"learn":[4.52579294],"iteration":277,"passed_time":0.3482727103,"remaining_time":0.9045068231},
{"learn":[4.521572155],"iteration":278,"passed_time":0.3495391801,"remaining_time":0.9032894224},
{"learn":[4.518818099],"iteration":279,"passed_time":0.3512129712,"remaining_time":0.9031190688},
{"learn":[4.514012334],"iteration":280,"passed_time":0.3524207851,"remaining_time":0.9017457098},
{"learn":[4.508331416],"iteration":281,"passed_time":0.3536656077,"remaining_time":0.900467753},
{"learn":[4.506038537],"iteration":282,"passed_time":0.3553798374,"remaining_time":0.9003793055},
{"learn":[4.505805643],"iteration":283,"passed_time":0.3565002895,"remaining_time":0.8987824201},
{"learn":[4.501550352],"iteration":284,"passed_time":0.3573764491,"remaining_time":0.8965760039},
{"learn":[4.494692643],"iteration":285,"passed_time":0.3583290563,"remaining_time":0.8945697419},
{"learn":[4.489330245],"iteration":286,"passed_time":0.3593296635,"remaining_time":0.8926900699},
{"learn":[4.484826955],"iteration":287,"passed_time":0.3605662888,"remaining_time":0.8913999917},
{"learn":[4.478285428],"iteration":288,"passed_time":0.3617302707,"remaining_time":0.8899315657},
{"learn":[4.475311671],"iteration":289,"passed_time":0.3627271091,"remaining_time":0.8880560257},
{"learn":[4.471581298],"iteration":290,"passed_time":0.363694572,"remaining_time":0.8861149537},
{"learn":[4.469164956],"iteration":291,"passed_time":0.3656508744,"remaining_time":0.8865781476},
{"learn":[4.462068024],"iteration":292,"passed_time":0.366916345,"remaining_time":0.88535787},
{"learn":[4.458540976],"iteration":293,"passed_time":0.36812814,"remaining_time":0.8840083906},
{"learn":[4.455757458],"iteration":294,"passed_time":0.3692696071,"remaining_time":0.8824917728},
{"learn":[4.453027414],"iteration":295,"passed_time":0.3713316682,"remaining_time":0.8831672108},
{"learn":[4.450659338],"iteration":296,"passed_time":0.3722512329,"remaining_time":0.8811199217},
{"learn":[4.444696901],"iteration":297,"passed_time":0.3732631589,"remaining_time":0.8792977769},
{"learn":[4.442052813],"iteration":298,"passed_time":0.3743794603,"remaining_time":0.877725758},
{"learn":[4.440036756],"iteration":299,"passed_time":0.3753963529,"remaining_time":0.8759248234},
{"learn":[4.435017051],"iteration":300,"passed_time":0.3764364422,"remaining_time":0.8741829672},
{"learn":[4.429962125],"iteration":301,"passed_time":0.3773444268,"remaining_time":0.8721404302},
{"learn":[4.427666256],"iteration":302,"passed_time":0.3783888755,"remaining_time":0.8704192944},
{"learn":[4.425030004],"iteration":303,"passed_time":0.3801499513,"remaining_time":0.8703433095},
{"learn":[4.422588771],"iteration":304,"passed_time":0.3813909702,"remaining_time":0.8690712272},
{"learn":[4.418936667],"iteration":305,"passed_time":0.3826782152,"remaining_time":0.8679041874},
{"learn":[4.416887976],"iteration":306,"passed_time":0.3842316021,"remaining_time":0.8673371344},
{"learn":[4.413773354],"iteration":307,"passed_time":0.385725083,"remaining_time":0.8666290826},
{"learn":[4.411129391],"iteration":308,"passed_time":0.3871499888,"remaining_time":0.8657625963},
{"learn":[4.40850819],"iteration":309,"passed_time":0.3881002283,"remaining_time":0.863835992},
{"learn":[4.404880292],"iteration":310,"passed_time":0.3889867564,"remaining_time":0.8617745182},
{"learn":[4.404593827],"iteration":311,"passed_time":0.3904244756,"remaining_time":0.8609360231},
{"learn":[4.402139942],"iteration":312,"passed_time":0.3920523893,"remaining_time":0.8605111547},
{"learn":[4.400284725],"iteration":313,"passed_time":0.3929958854,"remaining_time":0.8585833674},
{"learn":[4.395805521],"iteration":314,"passed_time":0.3946985703,"remaining_time":0.8583127641},
{"learn":[4.392838833],"iteration":315,"passed_time":0.3962473872,"remaining_time":0.8577000407},
{"learn":[4.389213061],"iteration":316,"passed_time":0.3976053309,"remaining_time":0.856670161},
{"learn":[4.3861981],"iteration":317,"passed_time":0.3989429532,"remaining_time":0.8555946354},
{"learn":[4.385054234],"iteration":318,"passed_time":0.4006108935,"remaining_time":0.8552226284},
{"learn":[4.379364607],"iteration":319,"passed_time":0.4020125054,"remaining_time":0.854276574},
{"learn":[4.378387619],"iteration":320,"passed_time":0.4034436402,"remaining_time":0.8533901298},
{"learn":[4.375816727],"iteration":321,"passed_time":0.4044515184,"remaining_time":0.8516090977},
{"learn":[4.374600202],"iteration":322,"passed_time":0.4054236247,"remaining_time":0.8497578759},
{"learn":[4.37098897],"iteration":323,"passed_time":0.4065552804,"remaining_time":0.8482449677},
{"learn":[4.367418484],"iteration":324,"passed_time":0.4076563479,"remaining_time":0.8466708765},
{"learn":[4.363584638],"iteration":325,"passed_time":0.4093647786,"remaining_time":0.8463554011},
{"learn":[4.360770706],"iteration":326,"passed_time":0.4107426725,"remaining_time":0.8453511272},
{"learn":[4.358675808],"iteration":327,"passed_time":0.4122024835,"remaining_time":0.8445124052},
{"learn":[4.354228195],"iteration":328,"passed_time":0.4144606238,"remaining_time":0.8452981111},
{"learn":[4.353773425],"iteration":329,"passed_time":0.4156999896,"remaining_time":0.8439969486},
{"learn":[4.351648009],"iteration":330,"passed_time":0.4167780844,"remaining_time":0.8423702068},
{"learn":[4.348209927],"iteration":331,"passed_time":0.4178193108,"remaining_time":0.8406725893},
{"learn":[4.345852733],"iteration":332,"passed_time":0.4189577157,"remaining_time":0.8391735626},
{"learn":[4.34237339],"iteration":333,"passed_time":0.4202715417,"remaining_time":0.8380264874},
{"learn":[4.340814362],"iteration":334,"passed_time":0.4212974218,"remaining_time":0.8363068224},
{"learn":[4.339707068],"iteration":335,"passed_time":0.422702529,"remaining_time":0.8353407121},
{"learn":[4.335430786],"iteration":336,"passed_time":0.4246297734,"remaining_time":0.8353992278},
{"learn":[4.33521887],"iteration":337,"passed_time":0.4257761554,"remaining_time":0.833916612},
{"learn":[4.328507238],"iteration":338,"passed_time":0.4270509921,"remaining_time":0.8326864476},
{"learn":[4.326140732],"iteration":339,"passed_time":0.4296949935,"remaining_time":0.8341138109},
{"learn":[4.323785636],"iteration":340,"passed_time":0.4310770534,"remaining_time":0.8330785284},
{"learn":[4.320632534],"iteration":341,"passed_time":0.4322372512,"remaining_time":0.8316143604},
{"learn":[4.31973724],"iteration":342,"passed_time":0.4332075222,"remaining_time":0.8297881693},
{"learn":[4.318000924],"iteration":343,"passed_time":0.4342839998,"remaining_time":0.8281694879},
{"learn":[4.312713628],"iteration":344,"passed_time":0.435364365,"remaining_time":0.8265613307},
{"learn":[4.308220789],"iteration":345,"passed_time":0.4362478236,"remaining_time":0.8245840364},
{"learn":[4.305890947],"iteration":346,"passed_time":0.4375772827,"remaining_time":0.8234523505},
{"learn":[4.305137856],"iteration":347,"passed_time":0.4396859306,"remaining_time":0.8237793873},
{"learn":[4.304787172],"iteration":348,"passed_time":0.4414013782,"remaining_time":0.8233590179},
{"learn":[4.30350134],"iteration":349,"passed_time":0.4425956552,"remaining_time":0.8219633596},
{"learn":[4.30293809],"iteration":350,"passed_time":0.444601643,"remaining_time":0.8220697046},
{"learn":[4.299548459],"iteration":351,"passed_time":0.4459967202,"remaining_time":0.8210394167},
{"learn":[4.294768408],"iteration":352,"passed_time":0.44711317,"remaining_time":0.8194963767},
{"learn":[4.294581479],"iteration":353,"passed_time":0.4483083981,"remaining_time":0.8180995062},
{"learn":[4.292551604],"iteration":354,"passed_time":0.4495895916,"remaining_time":0.8168599622},
{"learn":[4.288628894],"iteration":355,"passed_time":0.4505964669,"remaining_time":0.8151239457},
{"learn":[4.287802767],"iteration":356,"passed_time":0.4520147634,"remaining_time":0.8141330333},
{"learn":[4.284566905],"iteration":357,"passed_time":0.4540769777,"remaining_time":0.8142944685},
{"learn":[4.27890232],"iteration":358,"passed_time":0.4551991384,"remaining_time":0.8127650354},
{"learn":[4.276938023],"iteration":359,"passed_time":0.4570068067,"remaining_time":0.8124565453},
{"learn":[4.273425094],"iteration":360,"passed_time":0.458923944,"remaining_time":0.8123335185},
{"learn":[4.269726505],"iteration":361,"passed_time":0.4604679817,"remaining_time":0.8115430174},
{"learn":[4.265565857],"iteration":362,"passed_time":0.4615264732,"remaining_time":0.809896318},
{"learn":[4.262117173],"iteration":363,"passed_time":0.4634262746,"remaining_time":0.8097228314},
{"learn":[4.259185148],"iteration":364,"passed_time":0.4645225999,"remaining_time":0.8081420573},
{"learn":[4.257668507],"iteration":365,"passed_time":0.4656954003,"remaining_time":0.8066964037},
{"learn":[4.253432436],"iteration":366,"passed_time":0.4742332059,"remaining_time":0.817955366},
{"learn":[4.250216667],"iteration":367,"passed_time":0.4757725901,"remaining_time":0.817087709},
{"learn":[4.24514828],"iteration":368,"passed_time":0.4768265501,"remaining_time":0.8153863228},
{"learn":[4.244015772],"iteration":369,"passed_time":0.4778219625,"remaining_time":0.813588747},
{"learn":[4.240329192],"iteration":370,"passed_time":0.4788199982,"remaining_time":0.811799943},
{"learn":[4.236718014],"iteration":371,"passed_time":0.4797960202,"remaining_time":0.8099782276},
{"learn":[4.233495944],"iteration":372,"passed_time":0.4809753073,"remaining_time":0.8085027283},
{"learn":[4.230357491],"iteration":373,"passed_time":0.4846347679,"remaining_time":0.8111801196},
{"learn":[4.227381215],"iteration":374,"passed_time":0.4883895299,"remaining_time":0.8139825499},
{"learn":[4.226169067],"iteration":375,"passed_time":0.4893984454,"remaining_time":0.8121931648},
{"learn":[4.225963861],"iteration":376,"passed_time":0.4902519258,"remaining_time":0.8101510605},
{"learn":[4.224346548],"iteration":377,"passed_time":0.4911305376,"remaining_time":0.8081565989},
{"learn":[4.222595381],"iteration":378,"passed_time":0.4921541657,"remaining_time":0.8064056382},
{"learn":[4.219700938],"iteration":379,"passed_time":0.4931883625,"remaining_time":0.8046757493},
{"learn":[4.216356207],"iteration":380,"passed_time":0.4940824426,"remaining_time":0.8027218686},
{"learn":[4.214326494],"iteration":381,"passed_time":0.494885888,"remaining_time":0.8006269078},
{"learn":[4.212901398],"iteration":382,"passed_time":0.4958380842,"remaining_time":0.7987783237},
{"learn":[4.211331091],"iteration":383,"passed_time":0.4971964399,"remaining_time":0.7975859557},
{"learn":[4.208624791],"iteration":384,"passed_time":0.4993481423,"remaining_time":0.7976600195},
{"learn":[4.204659106],"iteration":385,"passed_time":0.500796624,"remaining_time":0.7966039563},
{"learn":[4.202968852],"iteration":386,"passed_time":0.5032032907,"remaining_time":0.7970636103},
{"learn":[4.197261935],"iteration":387,"passed_time":0.5048866909,"remaining_time":0.7963676671},
{"learn":[4.196934403],"iteration":388,"passed_time":0.5062221651,"remaining_time":0.7951201617},
{"learn":[4.192479929],"iteration":389,"passed_time":0.5074906958,"remaining_time":0.7937674985},
{"learn":[4.190243116],"iteration":390,"passed_time":0.5085735159,"remaining_time":0.7921260132},
{"learn":[4.185852431],"iteration":391,"passed_time":0.5096672818,"remaining_time":0.7905043554},
{"learn":[4.180967944],"iteration":392,"passed_time":0.5106792098,"remaining_time":0.7887589831},
{"learn":[4.178283162],"iteration":393,"passed_time":0.5124586059,"remaining_time":0.7881977543},
{"learn":[4.176341157],"iteration":394,"passed_time":0.5146334929,"remaining_time":0.7882361094},
{"learn":[4.176041504],"iteration":395,"passed_time":0.5158220685,"remaining_time":0.7867589125},
{"learn":[4.175564513],"iteration":396,"passed_time":0.5180673774,"remaining_time":0.7868882332},
{"learn":[4.170830274],"iteration":397,"passed_time":0.5312777743,"remaining_time":0.8035910054},
{"learn":[4.167804808],"iteration":398,"passed_time":0.5374048672,"remaining_time":0.8094744991},
{"learn":[4.165860548],"iteration":399,"passed_time":0.5386407789,"remaining_time":0.8079611684},
{"learn":[4.160950571],"iteration":400,"passed_time":0.5399602725,"remaining_time":0.8065740729},
{"learn":[4.158544115],"iteration":401,"passed_time":0.5412505596,"remaining_time":0.8051438673},
{"learn":[4.154448767],"iteration":402,"passed_time":0.544970877,"remaining_time":0.8073141776},
{"learn":[4.15197457],"iteration":403,"passed_time":0.5467019002,"remaining_time":0.806520625},
{"learn":[4.149562679],"iteration":404,"passed_time":0.5476010462,"remaining_time":0.8045003025},
{"learn":[4.149327961],"iteration":405,"passed_time":0.5486909398,"remaining_time":0.8027645769},
{"learn":[4.147444889],"iteration":406,"passed_time":0.5496575027,"remaining_time":0.8008523319},
{"learn":[4.147254809],"iteration":407,"passed_time":0.5505462348,"remaining_time":0.7988317916},
{"learn":[4.144589165],"iteration":408,"passed_time":0.5516828064,"remaining_time":0.797174911},
{"learn":[4.141691034],"iteration":409,"passed_time":0.5530676201,"remaining_time":0.7958777948},
{"learn":[4.138893468],"iteration":410,"passed_time":0.5544562814,"remaining_time":0.7945857657},
{"learn":[4.136964597],"iteration":411,"passed_time":0.5557085467,"remaining_time":0.7930986054},
{"learn":[4.133773523],"iteration":412,"passed_time":0.5572930557,"remaining_time":0.7920848031},
{"learn":[4.131363444],"iteration":413,"passed_time":0.5587075121,"remaining_time":0.7908275413},
{"learn":[4.130228592],"iteration":414,"passed_time":0.5607651226,"remaining_time":0.7904761366},
{"learn":[4.12884186],"iteration":415,"passed_time":0.5623043319,"remaining_time":0.7893887737},
{"learn":[4.12413494],"iteration":416,"passed_time":0.563292805,"remaining_time":0.7875292694},
{"learn":[4.119422508],"iteration":417,"passed_time":0.5643306112,"remaining_time":0.7857426213},
{"learn":[4.117038244],"iteration":418,"passed_time":0.5653310399,"remaining_time":0.7839077188},
{"learn":[4.116067631],"iteration":419,"passed_time":0.566226781,"remaining_time":0.7819322214},
{"learn":[4.110343455],"iteration":420,"passed_time":0.567906528,"remaining_time":0.7810400944},
{"learn":[4.105604544],"iteration":421,"passed_time":0.569544515,"remaining_time":0.7800870372},
{"learn":[4.103390131],"iteration":422,"passed_time":0.5705156607,"remaining_time":0.7782211258},
{"learn":[4.096724402],"iteration":423,"passed_time":0.5717509028,"remaining_time":0.7767182075},
{"learn":[4.093431279],"iteration":424,"passed_time":0.5736942783,"remaining_time":0.7761746118},
{"learn":[4.091412744],"iteration":425,"passed_time":0.5761070863,"remaining_time":0.776256966},
{"learn":[4.091192901],"iteration":426,"passed_time":0.5774066064,"remaining_time":0.7748336896},
{"learn":[4.088994581],"iteration":427,"passed_time":0.5784356168,"remaining_time":0.7730494692},
{"learn":[4.087845355],"iteration":428,"passed_time":0.5793569313,"remaining_time":0.7711254261},
{"learn":[4.083650279],"iteration":429,"passed_time":0.580250404,"remaining_time":0.7691691402},
{"learn":[4.079840652],"iteration":430,"passed_time":0.5823402277,"remaining_time":0.7687971916},
{"learn":[4.075707828],"iteration":431,"passed_time":0.5838002188,"remaining_time":0.7675891766},
{"learn":[4.071345409],"iteration":432,"passed_time":0.5849679902,"remaining_time":0.7659973452},
{"learn":[4.067460475],"iteration":433,"passed_time":0.5861701064,"remaining_time":0.7644522586},
{"learn":[4.064914749],"iteration":434,"passed_time":0.5897912395,"remaining_time":0.7660506904},
{"learn":[4.063823175],"iteration":435,"passed_time":0.5910478525,"remaining_time":0.7645664881},
{"learn":[4.058898471],"iteration":436,"passed_time":0.5919759426,"remaining_time":0.7626600816},
{"learn":[4.054120355],"iteration":437,"passed_time":0.5931764754,"remaining_time":0.761107715},
{"learn":[4.052715901],"iteration":438,"passed_time":0.5943249726,"remaining_time":0.7594904547},
{"learn":[4.052114167],"iteration":439,"passed_time":0.5957801412,"remaining_time":0.7582656343},
{"learn":[4.051377267],"iteration":440,"passed_time":0.5968764465,"remaining_time":0.7565848834},
{"learn":[4.049275336],"iteration":441,"passed_time":0.5982496224,"remaining_time":0.7552563107},
{"learn":[4.047099198],"iteration":442,"passed_time":0.5994722064,"remaining_time":0.7537381918},
{"learn":[4.044348685],"iteration":443,"passed_time":0.6005224515,"remaining_time":0.7520055924},
{"learn":[4.042822379],"iteration":444,"passed_time":0.6015175222,"remaining_time":0.7502072468},
{"learn":[4.041258611],"iteration":445,"passed_time":0.6029343326,"remaining_time":0.7489363682},
{"learn":[4.040044254],"iteration":446,"passed_time":0.6051811467,"remaining_time":0.7486916647},
{"learn":[4.036860137],"iteration":447,"passed_time":0.6062329488,"remaining_time":0.7469655976},
{"learn":[4.036372284],"iteration":448,"passed_time":0.6078337633,"remaining_time":0.7459162663},
{"learn":[4.03368231],"iteration":449,"passed_time":0.6089052483,"remaining_time":0.7442175256},
{"learn":[4.032439519],"iteration":450,"passed_time":0.6102706938,"remaining_time":0.7428794033},
{"learn":[4.032008634],"iteration":451,"passed_time":0.6113709089,"remaining_time":0.7412195975},
{"learn":[4.030034932],"iteration":452,"passed_time":0.6122971013,"remaining_time":0.739352129},
{"learn":[4.028173412],"iteration":453,"passed_time":0.613263557,"remaining_time":0.7375372294},
{"learn":[4.023806097],"iteration":454,"passed_time":0.6142958335,"remaining_time":0.7358048994},
{"learn":[4.020239186],"iteration":455,"passed_time":0.6152363841,"remaining_time":0.7339662126},
{"learn":[4.017384838],"iteration":456,"passed_time":0.6161530884,"remaining_time":0.7321031226},
{"learn":[4.016468229],"iteration":457,"passed_time":0.6179840274,"remaining_time":0.7313260761},
{"learn":[4.014530169],"iteration":458,"passed_time":0.6198538432,"remaining_time":0.7305902597},
{"learn":[4.012884822],"iteration":459,"passed_time":0.6219735775,"remaining_time":0.7301428953},
{"learn":[4.008924707],"iteration":460,"passed_time":0.6229391295,"remaining_time":0.7283388087},
{"learn":[4.008286778],"iteration":461,"passed_time":0.6239068253,"remaining_time":0.7265408485},
{"learn":[4.006444202],"iteration":462,"passed_time":0.6248926027,"remaining_time":0.7247674463},
{"learn":[4.003284363],"iteration":463,"passed_time":0.6258298001,"remaining_time":0.7229413208},
{"learn":[3.999811484],"iteration":464,"passed_time":0.6268150002,"remaining_time":0.7211742476},
{"learn":[3.997483319],"iteration":465,"passed_time":0.6277146655,"remaining_time":0.7193125137},
{"learn":[3.99708333],"iteration":466,"passed_time":0.6286816055,"remaining_time":0.7175316825},
{"learn":[3.995860263],"iteration":467,"passed_time":0.6296117025,"remaining_time":0.7157124482},
{"learn":[3.994131111],"iteration":468,"passed_time":0.6305065748,"remaining_time":0.7138571242},
{"learn":[3.993125499],"iteration":469,"passed_time":0.6318924818,"remaining_time":0.7125596071},
{"learn":[3.992954084],"iteration":470,"passed_time":0.6334820716,"remaining_time":0.7114904795},
{"learn":[3.990635743],"iteration":471,"passed_time":0.6348372393,"remaining_time":0.7101569118},
{"learn":[3.986678254],"iteration":472,"passed_time":0.6377141317,"remaining_time":0.7105187048},
{"learn":[3.986393291],"iteration":473,"passed_time":0.6387541656,"remaining_time":0.7088284622},
{"learn":[3.986152671],"iteration":474,"passed_time":0.6399142318,"remaining_time":0.7072736246},
{"learn":[3.985596662],"iteration":475,"passed_time":0.6407838666,"remaining_time":0.7054007271},
{"learn":[3.983853457],"iteration":476,"passed_time":0.6418570708,"remaining_time":0.7037552369},
{"learn":[3.983263928],"iteration":477,"passed_time":0.6427592283,"remaining_time":0.7019253498},
{"learn":[3.980067202],"iteration":478,"passed_time":0.6439450813,"remaining_time":0.7004079068},
{"learn":[3.978115407],"iteration":479,"passed_time":0.6449813696,"remaining_time":0.6987298171},
{"learn":[3.972661644],"iteration":480,"passed_time":0.6466167164,"remaining_time":0.6977007813},
{"learn":[3.969938254],"iteration":481,"passed_time":0.6483073728,"remaining_time":0.6967286704},
{"learn":[3.968211434],"iteration":482,"passed_time":0.6495665415,"remaining_time":0.6952917225},
{"learn":[3.966113368],"iteration":483,"passed_time":0.6509485127,"remaining_time":0.6939864309},
{"learn":[3.962246044],"iteration":484,"passed_time":0.6520384913,"remaining_time":0.6923707691},
{"learn":[3.961319703],"iteration":485,"passed_time":0.653166273,"remaining_time":0.6907972517},
{"learn":[3.96078191],"iteration":486,"passed_time":0.6541402997,"remaining_time":0.6890636011},
{"learn":[3.958913633],"iteration":487,"passed_time":0.6551092784,"remaining_time":0.6873277675},
{"learn":[3.957428286],"iteration":488,"passed_time":0.6560981127,"remaining_time":0.6856158192},
{"learn":[3.952641965],"iteration":489,"passed_time":0.6570622841,"remaining_time":0.6838811529},
{"learn":[3.951486786],"iteration":490,"passed_time":0.6581384216,"remaining_time":0.6822656957},
{"learn":[3.94938344],"iteration":491,"passed_time":0.6591784423,"remaining_time":0.6806151396},
{"learn":[3.947297924],"iteration":492,"passed_time":0.6605777694,"remaining_time":0.6793365702},
{"learn":[3.946284886],"iteration":493,"passed_time":0.6624717369,"remaining_time":0.6785641677},
{"learn":[3.943288204],"iteration":494,"passed_time":0.6637649869,"remaining_time":0.6771743805},
{"learn":[3.943076488],"iteration":495,"passed_time":0.665053623,"remaining_time":0.6757802943},
{"learn":[3.942347078],"iteration":496,"passed_time":0.6666697527,"remaining_time":0.6747180796},
{"learn":[3.940251541],"iteration":497,"passed_time":0.6679858999,"remaining_time":0.6733512485},
{"learn":[3.939011019],"iteration":498,"passed_time":0.6690141825,"remaining_time":0.6716956021},
{"learn":[3.938760512],"iteration":499,"passed_time":0.6698995334,"remaining_time":0.6698995334},
{"learn":[3.934522727],"iteration":500,"passed_time":0.6708809636,"remaining_time":0.6682027961},
{"learn":[3.930091193],"iteration":501,"passed_time":0.6719410317,"remaining_time":0.6665869199},
{"learn":[3.927671752],"iteration":502,"passed_time":0.6728770878,"remaining_time":0.664850721},
{"learn":[3.927280041],"iteration":503,"passed_time":0.6738525109,"remaining_time":0.6631564393},
{"learn":[3.925987561],"iteration":504,"passed_time":0.6752424408,"remaining_time":0.6618713033},
{"learn":[3.921645957],"iteration":505,"passed_time":0.6771398327,"remaining_time":0.6610811805},
{"learn":[3.920333743],"iteration":506,"passed_time":0.6784450838,"remaining_time":0.6597109},
{"learn":[3.918659461],"iteration":507,"passed_time":0.679793889,"remaining_time":0.6583830578},
{"learn":[3.916124385],"iteration":508,"passed_time":0.681098436,"remaining_time":0.6570124402},
{"learn":[3.913849268],"iteration":509,"passed_time":0.6824594567,"remaining_time":0.6556963408},
{"learn":[3.912826119],"iteration":510,"passed_time":0.6834344594,"remaining_time":0.6540106666},
{"learn":[3.910034145],"iteration":511,"passed_time":0.68438245,"remaining_time":0.6523020227},
{"learn":[3.90792379],"iteration":512,"passed_time":0.6854195955,"remaining_time":0.6506809805},
{"learn":[3.907823851],"iteration":513,"passed_time":0.6863281272,"remaining_time":0.6489406028},
{"learn":[3.904527401],"iteration":514,"passed_time":0.6873459019,"remaining_time":0.6473063348},
{"learn":[3.903378283],"iteration":515,"passed_time":0.6884510435,"remaining_time":0.6457564052},
{"learn":[3.902170135],"iteration":516,"passed_time":0.6901500399,"remaining_time":0.6447629967},
{"learn":[3.899435429],"iteration":517,"passed_time":0.691966082,"remaining_time":0.6438757751},
{"learn":[3.897497505],"iteration":518,"passed_time":0.693534931,"remaining_time":0.6427558801},
{"learn":[3.896426119],"iteration":519,"passed_time":0.6955408781,"remaining_time":0.6420377337},
{"learn":[3.896044669],"iteration":520,"passed_time":0.6965022715,"remaining_time":0.6403542957},
{"learn":[3.892795942],"iteration":521,"passed_time":0.6974990338,"remaining_time":0.6387060118},
{"learn":[3.892413888],"iteration":522,"passed_time":0.6985105124,"remaining_time":0.6370736414},
{"learn":[3.891738985],"iteration":523,"passed_time":0.6994590798,"remaining_time":0.6353864923},
{"learn":[3.88822057],"iteration":524,"passed_time":0.7004868464,"remaining_time":0.6337738134},
{"learn":[3.883837053],"iteration":525,"passed_time":0.7014098146,"remaining_time":0.6320689203},
{"learn":[3.881769742],"iteration":526,"passed_time":0.7024202691,"remaining_time":0.6304455166},
{"learn":[3.880356898],"iteration":527,"passed_time":0.7035640563,"remaining_time":0.6289436261},
{"learn":[3.879250273],"iteration":528,"passed_time":0.7054789483,"remaining_time":0.6281296497},
{"learn":[3.877174493],"iteration":529,"passed_time":0.7067920788,"remaining_time":0.6267778812},
{"learn":[3.875854201],"iteration":530,"passed_time":0.7079736591,"remaining_time":0.625310068},
{"learn":[3.873189396],"iteration":531,"passed_time":0.7098263387,"remaining_time":0.6244336965},
{"learn":[3.871583368],"iteration":532,"passed_time":0.711701595,"remaining_time":0.6235734425},
{"learn":[3.869622679],"iteration":533,"passed_time":0.7126791972,"remaining_time":0.621926041},
{"learn":[3.866860164],"iteration":534,"passed_time":0.7135803186,"remaining_time":0.6202146694},
{"learn":[3.864498444],"iteration":535,"passed_time":0.7145353436,"remaining_time":0.618552984},
{"learn":[3.861416322],"iteration":536,"passed_time":0.7157761328,"remaining_time":0.6171403156},
{"learn":[3.860265769],"iteration":537,"passed_time":0.7169041955,"remaining_time":0.6156314839},
{"learn":[3.859328725],"iteration":538,"passed_time":0.7178936858,"remaining_time":0.6140055457},
{"learn":[3.858521278],"iteration":539,"passed_time":0.7192906722,"remaining_time":0.6127290911},
{"learn":[3.85599111],"iteration":540,"passed_time":0.7208750671,"remaining_time":0.6116111937},
{"learn":[3.852379816],"iteration":541,"passed_time":0.7227523377,"remaining_time":0.6107390603},
{"learn":[3.851327537],"iteration":542,"passed_time":0.7248825731,"remaining_time":0.610076125},
{"learn":[3.847854898],"iteration":543,"passed_time":0.7259812883,"remaining_time":0.6085431387},
{"learn":[3.847083414],"iteration":544,"passed_time":0.7269086875,"remaining_time":0.6068687208},
{"learn":[3.845397429],"iteration":545,"passed_time":0.7278859443,"remaining_time":0.6052384958},
{"learn":[3.841933528],"iteration":546,"passed_time":0.7287687274,"remaining_time":0.6035324196},
{"learn":[3.840996474],"iteration":547,"passed_time":0.7297338168,"remaining_time":0.6018972357},
{"learn":[3.838355966],"iteration":548,"passed_time":0.7309072108,"remaining_time":0.600435614},
{"learn":[3.83342799],"iteration":549,"passed_time":0.7319422711,"remaining_time":0.5988618582},
{"learn":[3.828161535],"iteration":550,"passed_time":0.7361122027,"remaining_time":0.599844608},
{"learn":[3.823502399],"iteration":551,"passed_time":0.7380505899,"remaining_time":0.5989975802},
{"learn":[3.820068862],"iteration":552,"passed_time":0.739662684,"remaining_time":0.5978828567},
{"learn":[3.817951642],"iteration":553,"passed_time":0.740774802,"remaining_time":0.5963638298},
{"learn":[3.815785958],"iteration":554,"passed_time":0.7418318697,"remaining_time":0.5948021297},
{"learn":[3.81503012],"iteration":555,"passed_time":0.7427990737,"remaining_time":0.5931704833},
{"learn":[3.813529315],"iteration":556,"passed_time":0.7437706392,"remaining_time":0.5915446915},
{"learn":[3.808881326],"iteration":557,"passed_time":0.744752164,"remaining_time":0.5899291335},
{"learn":[3.808740434],"iteration":558,"passed_time":0.7457268889,"remaining_time":0.5883104794},
{"learn":[3.80714352],"iteration":559,"passed_time":0.7469627135,"remaining_time":0.5868992749},
{"learn":[3.80573346],"iteration":560,"passed_time":0.7519516613,"remaining_time":0.5884256316},
{"learn":[3.803370052],"iteration":561,"passed_time":0.7539751319,"remaining_time":0.5876176295},
{"learn":[3.803215211],"iteration":562,"passed_time":0.7551893569,"remaining_time":0.586177174},
{"learn":[3.801309667],"iteration":563,"passed_time":0.7564161999,"remaining_time":0.5847472751},
{"learn":[3.800003847],"iteration":564,"passed_time":0.7573530128,"remaining_time":0.5830947975},
{"learn":[3.798026138],"iteration":565,"passed_time":0.7584452672,"remaining_time":0.5815640388},
{"learn":[3.794745847],"iteration":566,"passed_time":0.7595860244,"remaining_time":0.580071867},
{"learn":[3.794312041],"iteration":567,"passed_time":0.7606166404,"remaining_time":0.5784971631},
{"learn":[3.792205926],"iteration":568,"passed_time":0.7616979098,"remaining_time":0.5769627401},
{"learn":[3.788991061],"iteration":569,"passed_time":0.7627447293,"remaining_time":0.5754039186},
{"learn":[3.787391572],"iteration":570,"passed_time":0.7644236958,"remaining_time":0.574321831},
{"learn":[3.7826445],"iteration":571,"passed_time":0.7658440004,"remaining_time":0.5730441122},
{"learn":[3.781700331],"iteration":572,"passed_time":0.7679444319,"remaining_time":0.5722727267},
{"learn":[3.780045374],"iteration":573,"passed_time":0.7698291441,"remaining_time":0.5713366122},
{"learn":[3.775462644],"iteration":574,"passed_time":0.7708217341,"remaining_time":0.5697378034},
{"learn":[3.773711943],"iteration":575,"passed_time":0.7718574139,"remaining_time":0.5681728186},
{"learn":[3.772415806],"iteration":576,"passed_time":0.7728523789,"remaining_time":0.5665798203},
{"learn":[3.770170875],"iteration":577,"passed_time":0.773810003,"remaining_time":0.5649616285},
{"learn":[3.765166479],"iteration":578,"passed_time":0.7747530549,"remaining_time":0.5633351228},
{"learn":[3.763976102],"iteration":579,"passed_time":0.7758504529,"remaining_time":0.5618227417},
{"learn":[3.760761708],"iteration":580,"passed_time":0.7768814782,"remaining_time":0.5602639232},
{"learn":[3.758155662],"iteration":581,"passed_time":0.7780686547,"remaining_time":0.5588190682},
{"learn":[3.756844548],"iteration":582,"passed_time":0.7802035826,"remaining_time":0.5580529914},
{"learn":[3.753098923],"iteration":583,"passed_time":0.7820646624,"remaining_time":0.5570871568},
{"learn":[3.751618946],"iteration":584,"passed_time":0.7844022766,"remaining_time":0.5564563159},
{"learn":[3.751398464],"iteration":585,"passed_time":0.7853894905,"remaining_time":0.5548656128},
{"learn":[3.749920103],"iteration":586,"passed_time":0.786267581,"remaining_time":0.553200189},
{"learn":[3.748237465],"iteration":587,"passed_time":0.7872018187,"remaining_time":0.5515767845},
{"learn":[3.746021536],"iteration":588,"passed_time":0.7881453275,"remaining_time":0.5499621895},
{"learn":[3.74417648],"iteration":589,"passed_time":0.7889822732,"remaining_time":0.548275817},
{"learn":[3.738788389],"iteration":590,"passed_time":0.7899380894,"remaining_time":0.546674583},
{"learn":[3.736021611],"iteration":591,"passed_time":0.7909041294,"remaining_time":0.5450825757},
{"learn":[3.734546151],"iteration":592,"passed_time":0.7919207643,"remaining_time":0.5435274049},
{"learn":[3.733527479],"iteration":593,"passed_time":0.7932019636,"remaining_time":0.5421548775},
{"learn":[3.733026392],"iteration":594,"passed_time":0.7952405935,"remaining_time":0.5412982191},
{"learn":[3.730314752],"iteration":595,"passed_time":0.7981659581,"remaining_time":0.5410386696},
{"learn":[3.727342596],"iteration":596,"passed_time":0.7992591895,"remaining_time":0.5395334227},
{"learn":[3.725459604],"iteration":597,"passed_time":0.8003765599,"remaining_time":0.5380457811},
{"learn":[3.723158842],"iteration":598,"passed_time":0.8013167266,"remaining_time":0.5364407468},
{"learn":[3.722362756],"iteration":599,"passed_time":0.8022426444,"remaining_time":0.5348284296},
{"learn":[3.721443615],"iteration":600,"passed_time":0.803200711,"remaining_time":0.5332397399},
{"learn":[3.720743486],"iteration":601,"passed_time":0.8043525471,"remaining_time":0.5317812521},
{"learn":[3.720215334],"iteration":602,"passed_time":0.8055203713,"remaining_time":0.5303343075},
{"learn":[3.719436563],"iteration":603,"passed_time":0.8064184453,"remaining_time":0.528711431},
{"learn":[3.715046574],"iteration":604,"passed_time":0.8100439899,"remaining_time":0.5288716959},
{"learn":[3.71443396],"iteration":605,"passed_time":0.8114612825,"remaining_time":0.5275837381},
{"learn":[3.712938941],"iteration":606,"passed_time":0.8140864618,"remaining_time":0.5270773962},
{"learn":[3.712814764],"iteration":607,"passed_time":0.8152117861,"remaining_time":0.5255970726},
{"learn":[3.71235348],"iteration":608,"passed_time":0.8162857592,"remaining_time":0.5240849455},
{"learn":[3.711223749],"iteration":609,"passed_time":0.8173222798,"remaining_time":0.5225503101},
{"learn":[3.710755648],"iteration":610,"passed_time":0.8182669859,"remaining_time":0.5209588503},
{"learn":[3.708668039],"iteration":611,"passed_time":0.8192533786,"remaining_time":0.5193959329},
{"learn":[3.705623591],"iteration":612,"passed_time":0.8202611121,"remaining_time":0.5178483693},
{"learn":[3.704045802],"iteration":613,"passed_time":0.821336019,"remaining_time":0.5163447937},
{"learn":[3.699915209],"iteration":614,"passed_time":0.8252381619,"remaining_time":0.5166125078},
{"learn":[3.696182221],"iteration":615,"passed_time":0.8278726366,"remaining_time":0.5160764488},
{"learn":[3.694263278],"iteration":616,"passed_time":0.829314563,"remaining_time":0.5147933187},
{"learn":[3.693810229],"iteration":617,"passed_time":0.8304679899,"remaining_time":0.5133313465},
{"learn":[3.690900932],"iteration":618,"passed_time":0.8316107747,"remaining_time":0.5118638209},
{"learn":[3.688020895],"iteration":619,"passed_time":0.8326810043,"remaining_time":0.5103528736},
{"learn":[3.685491894],"iteration":620,"passed_time":0.8335537916,"remaining_time":0.5087228454},
{"learn":[3.684328128],"iteration":621,"passed_time":0.8345973355,"remaining_time":0.5071990238},
{"learn":[3.680640153],"iteration":622,"passed_time":0.8356335155,"remaining_time":0.5056722879},
{"learn":[3.678932783],"iteration":623,"passed_time":0.836642158,"remaining_time":0.5041305311},
{"learn":[3.674167041],"iteration":624,"passed_time":0.8379658429,"remaining_time":0.5027795058},
{"learn":[3.672200976],"iteration":625,"passed_time":0.8400381723,"remaining_time":0.501875841},
{"learn":[3.670606604],"iteration":626,"passed_time":0.8413917255,"remaining_time":0.5005408511},
{"learn":[3.665506042],"iteration":627,"passed_time":0.8431390051,"remaining_time":0.4994390285},
{"learn":[3.664214007],"iteration":628,"passed_time":0.8446989273,"remaining_time":0.4982246455},
{"learn":[3.66261643],"iteration":629,"passed_time":0.8458835782,"remaining_time":0.4967887682},
{"learn":[3.662118449],"iteration":630,"passed_time":0.8469559732,"remaining_time":0.4952880414},
{"learn":[3.660871366],"iteration":631,"passed_time":0.8480978169,"remaining_time":0.4938291085},
{"learn":[3.656695243],"iteration":632,"passed_time":0.8493356643,"remaining_time":0.4924268385},
{"learn":[3.654497801],"iteration":633,"passed_time":0.8504669202,"remaining_time":0.4909635533},
{"learn":[3.654189134],"iteration":634,"passed_time":0.8514567284,"remaining_time":0.4894200092},
{"learn":[3.653957699],"iteration":635,"passed_time":0.8530800789,"remaining_time":0.4882407999},
{"learn":[3.651920725],"iteration":636,"passed_time":0.8550341869,"remaining_time":0.4872486811},
{"learn":[3.65106705],"iteration":637,"passed_time":0.8561212976,"remaining_time":0.485761614},
{"learn":[3.650612844],"iteration":638,"passed_time":0.8578495776,"remaining_time":0.4846380243},
{"learn":[3.649884732],"iteration":639,"passed_time":0.8590351475,"remaining_time":0.4832072705},
{"learn":[3.646276182],"iteration":640,"passed_time":0.8602755311,"remaining_time":0.4818079808},
{"learn":[3.645808194],"iteration":641,"passed_time":0.8613884323,"remaining_time":0.4803380978},
{"learn":[3.645042989],"iteration":642,"passed_time":0.8626616524,"remaining_time":0.4789583358},
{"learn":[3.639864499],"iteration":643,"passed_time":0.8638692212,"remaining_time":0.4775426129},
{"learn":[3.637318478],"iteration":644,"passed_time":0.8648804388,"remaining_time":0.4760194663},
{"learn":[3.636344905],"iteration":645,"passed_time":0.8658674474,"remaining_time":0.4744846383},
{"learn":[3.634754643],"iteration":646,"passed_time":0.866954377,"remaining_time":0.4730060202},
{"learn":[3.630724975],"iteration":647,"passed_time":0.8689274127,"remaining_time":0.4720099526},
{"learn":[3.629408252],"iteration":648,"passed_time":0.8701168692,"remaining_time":0.4705870895},
{"learn":[3.62790646],"iteration":649,"passed_time":0.8715995506,"remaining_time":0.4693228349},
{"learn":[3.627388973],"iteration":650,"passed_time":0.8727798807,"remaining_time":0.4678958193},
{"learn":[3.625163557],"iteration":651,"passed_time":0.8739144856,"remaining_time":0.4664451549},
{"learn":[3.623701985],"iteration":652,"passed_time":0.8749974789,"remaining_time":0.4649680324},
{"learn":[3.622342639],"iteration":653,"passed_time":0.8767556963,"remaining_time":0.4638493439},
{"learn":[3.621130639],"iteration":654,"passed_time":0.8780816154,"remaining_time":0.4625010035},
{"learn":[3.619125665],"iteration":655,"passed_time":0.8792250344,"remaining_time":0.4610570303},
{"learn":[3.618878783],"iteration":656,"passed_time":0.880436352,"remaining_time":0.4596494197},
{"learn":[3.616207429],"iteration":657,"passed_time":0.8817974783,"remaining_time":0.4583202699},
{"learn":[3.61206486],"iteration":658,"passed_time":0.8840488113,"remaining_time":0.4574516611},
{"learn":[3.611955873],"iteration":659,"passed_time":0.8854801051,"remaining_time":0.4561564178},
{"learn":[3.610713743],"iteration":660,"passed_time":0.88717079,"remaining_time":0.454993794},
{"learn":[3.610044025],"iteration":661,"passed_time":0.8882881356,"remaining_time":0.4535368426},
{"learn":[3.607342669],"iteration":662,"passed_time":0.8895686282,"remaining_time":0.4521638427},
{"learn":[3.602510618],"iteration":663,"passed_time":0.8906951793,"remaining_time":0.4507132233},
{"learn":[3.600492392],"iteration":664,"passed_time":0.891874647,"remaining_time":0.4492902357},
{"learn":[3.597171065],"iteration":665,"passed_time":0.8931400479,"remaining_time":0.4479110751},
{"learn":[3.594358798],"iteration":666,"passed_time":0.8943932306,"remaining_time":0.4465261556},
{"learn":[3.593945251],"iteration":667,"passed_time":0.8954176107,"remaining_time":0.4450279143},
{"learn":[3.593607748],"iteration":668,"passed_time":0.898530003,"remaining_time":0.4445641719},
{"learn":[3.592238714],"iteration":669,"passed_time":0.8998413969,"remaining_time":0.4432054642},
{"learn":[3.590144654],"iteration":670,"passed_time":0.9021526429,"remaining_time":0.4423371379},
{"learn":[3.587151536],"iteration":671,"passed_time":0.9033801513,"remaining_time":0.44093555},
{"learn":[3.586070865],"iteration":672,"passed_time":0.904799416,"remaining_time":0.4396276509},
{"learn":[3.585102746],"iteration":673,"passed_time":0.9060596838,"remaining_time":0.4382425177},
{"learn":[3.584362847],"iteration":674,"passed_time":0.9072700301,"remaining_time":0.4368337182},
{"learn":[3.581407561],"iteration":675,"passed_time":0.9084926056,"remaining_time":0.4354313672},
{"learn":[3.57919422],"iteration":676,"passed_time":0.9095132756,"remaining_time":0.4339332171},
{"learn":[3.577632204],"iteration":677,"passed_time":0.9104912887,"remaining_time":0.4324162167},
{"learn":[3.573911195],"iteration":678,"passed_time":0.912078186,"remaining_time":0.4311886564},
{"learn":[3.573408216],"iteration":679,"passed_time":0.9147418582,"remaining_time":0.4304667568},
{"learn":[3.571076482],"iteration":680,"passed_time":0.9158458607,"remaining_time":0.4290085603},
{"learn":[3.568177107],"iteration":681,"passed_time":0.9174916199,"remaining_time":0.4278040104},
{"learn":[3.564824621],"iteration":682,"passed_time":0.9186602131,"remaining_time":0.4263767021},
{"learn":[3.562475026],"iteration":683,"passed_time":0.9200747102,"remaining_time":0.425063755},
{"learn":[3.561226889],"iteration":684,"passed_time":0.9216010275,"remaining_time":0.4238019323},
{"learn":[3.559383467],"iteration":685,"passed_time":0.9227391556,"remaining_time":0.4223616543},
{"learn":[3.555209766],"iteration":686,"passed_time":0.9237349218,"remaining_time":0.4208573952},
{"learn":[3.55345383],"iteration":687,"passed_time":0.9247991395,"remaining_time":0.4193856563},
{"learn":[3.552300968],"iteration":688,"passed_time":0.9259582065,"remaining_time":0.4179579133},
{"learn":[3.551253986],"iteration":689,"passed_time":0.9383544551,"remaining_time":0.4215795378},
{"learn":[3.549807725],"iteration":690,"passed_time":0.9399752299,"remaining_time":0.4203362461},
{"learn":[3.547992926],"iteration":691,"passed_time":0.9419691363,"remaining_time":0.4192579393},
{"learn":[3.545438607],"iteration":692,"passed_time":0.944314612,"remaining_time":0.4183327357},
{"learn":[3.543313763],"iteration":693,"passed_time":0.9458837672,"remaining_time":0.4170611423},
{"learn":[3.542962896],"iteration":694,"passed_time":0.9474049431,"remaining_time":0.4157676369},
{"learn":[3.539800465],"iteration":695,"passed_time":0.9489509866,"remaining_time":0.414484339},
{"learn":[3.53953187],"iteration":696,"passed_time":0.9520714004,"remaining_time":0.4138846977},
{"learn":[3.536332425],"iteration":697,"passed_time":0.9538860017,"remaining_time":0.4127128546},
{"learn":[3.534993327],"iteration":698,"passed_time":0.9556753043,"remaining_time":0.4115282784},
{"learn":[3.531637011],"iteration":699,"passed_time":0.9582569533,"remaining_time":0.4106815514},
{"learn":[3.531040284],"iteration":700,"passed_time":0.9617581157,"remaining_time":0.4102220779},
{"learn":[3.529973872],"iteration":701,"passed_time":0.9810075862,"remaining_time":0.4164391178},
{"learn":[3.527325183],"iteration":702,"passed_time":0.982772923,"remaining_time":0.4151970955},
{"learn":[3.527200815],"iteration":703,"passed_time":0.9844645924,"remaining_time":0.4139226127},
{"learn":[3.523459911],"iteration":704,"passed_time":0.9859635491,"remaining_time":0.4125663078},
{"learn":[3.522729934],"iteration":705,"passed_time":0.9944088293,"remaining_time":0.4141022604},
{"learn":[3.522260582],"iteration":706,"passed_time":0.9961093663,"remaining_time":0.4128147727},
{"learn":[3.518641591],"iteration":707,"passed_time":0.9983335462,"remaining_time":0.411742084},
{"learn":[3.516856405],"iteration":708,"passed_time":0.9998073948,"remaining_time":0.4103581832},
{"learn":[3.515083413],"iteration":709,"passed_time":1.001262137,"remaining_time":0.408966225},
{"learn":[3.514671214],"iteration":710,"passed_time":1.005001582,"remaining_time":0.4085027529},
{"learn":[3.512617621],"iteration":711,"passed_time":1.006306601,"remaining_time":0.4070453667},
{"learn":[3.510747971],"iteration":712,"passed_time":1.007767023,"remaining_time":0.4056509614},
{"learn":[3.508149266],"iteration":713,"passed_time":1.009116043,"remaining_time":0.4042117485},
{"learn":[3.504557165],"iteration":714,"passed_time":1.011296501,"remaining_time":0.4031041996},
{"learn":[3.501367208],"iteration":715,"passed_time":1.013980677,"remaining_time":0.4021934529},
{"learn":[3.497593362],"iteration":716,"passed_time":1.015629926,"remaining_time":0.4008692736},
{"learn":[3.496291169],"iteration":717,"passed_time":1.017091863,"remaining_time":0.3994706201},
{"learn":[3.49330374],"iteration":718,"passed_time":1.020276291,"remaining_time":0.398744976},
{"learn":[3.490044385],"iteration":719,"passed_time":1.023860438,"remaining_time":0.3981679483},
{"learn":[3.488891789],"iteration":720,"passed_time":1.025012033,"remaining_time":0.396641272},
{"learn":[3.486869081],"iteration":721,"passed_time":1.026192856,"remaining_time":0.395126889},
{"learn":[3.486303638],"iteration":722,"passed_time":1.028915225,"remaining_time":0.3942040352},
{"learn":[3.486035862],"iteration":723,"passed_time":1.030646871,"remaining_time":0.3928985311},
{"learn":[3.482668951],"iteration":724,"passed_time":1.033180109,"remaining_time":0.3918959033},
{"learn":[3.47820549],"iteration":725,"passed_time":1.035270965,"remaining_time":0.3907220996},
{"learn":[3.474392283],"iteration":726,"passed_time":1.037898031,"remaining_time":0.3897471287},
{"learn":[3.472268163],"iteration":727,"passed_time":1.039410504,"remaining_time":0.3883511775},
{"learn":[3.471209164],"iteration":728,"passed_time":1.058286192,"remaining_time":0.3934095448},
{"learn":[3.470049971],"iteration":729,"passed_time":1.060059826,"remaining_time":0.3920769219},
{"learn":[3.469078654],"iteration":730,"passed_time":1.062651373,"remaining_time":0.3910440759},
{"learn":[3.468643292],"iteration":731,"passed_time":1.065105504,"remaining_time":0.3899566598},
{"learn":[3.468134848],"iteration":732,"passed_time":1.066571277,"remaining_time":0.3885054992},
{"learn":[3.467820182],"iteration":733,"passed_time":1.067915554,"remaining_time":0.3870102688},
{"learn":[3.465776156],"iteration":734,"passed_time":1.06927727,"remaining_time":0.385521737},
{"learn":[3.463037608],"iteration":735,"passed_time":1.070701811,"remaining_time":0.3840560843},
{"learn":[3.45965637],"iteration":736,"passed_time":1.07280563,"remaining_time":0.3828329452},
{"learn":[3.457275091],"iteration":737,"passed_time":1.074575196,"remaining_time":0.3814887553},
{"learn":[3.455522955],"iteration":738,"passed_time":1.076347551,"remaining_time":0.3801443991},
{"learn":[3.451270508],"iteration":739,"passed_time":1.078094444,"remaining_time":0.3787899399},
{"learn":[3.450978947],"iteration":740,"passed_time":1.079459119,"remaining_time":0.3773008256},
{"learn":[3.450608492],"iteration":741,"passed_time":1.081448626,"remaining_time":0.3760293066},
{"learn":[3.448122004],"iteration":742,"passed_time":1.082888679,"remaining_time":0.3745658016},
{"learn":[3.445646714],"iteration":743,"passed_time":1.084210459,"remaining_time":0.3730616634},
{"learn":[3.44411263],"iteration":744,"passed_time":1.085653571,"remaining_time":0.3715995446},
{"learn":[3.443264164],"iteration":745,"passed_time":1.087549207,"remaining_time":0.3702915532},
{"learn":[3.439521363],"iteration":746,"passed_time":1.096369289,"remaining_time":0.3713272156},
{"learn":[3.436809225],"iteration":747,"passed_time":1.098098589,"remaining_time":0.369947653},
{"learn":[3.435509465],"iteration":748,"passed_time":1.099715523,"remaining_time":0.3685295011},
{"learn":[3.434450277],"iteration":749,"passed_time":1.101282028,"remaining_time":0.3670940094},
{"learn":[3.431786753],"iteration":750,"passed_time":1.103044374,"remaining_time":0.3657231012},
{"learn":[3.430150302],"iteration":751,"passed_time":1.105942093,"remaining_time":0.3647255838},
{"learn":[3.42696281],"iteration":752,"passed_time":1.108160018,"remaining_time":0.3635000324},
{"learn":[3.426870334],"iteration":753,"passed_time":1.110231411,"remaining_time":0.3622240412},
{"learn":[3.425200309],"iteration":754,"passed_time":1.112903188,"remaining_time":0.3611407696},
{"learn":[3.423383783],"iteration":755,"passed_time":1.116896171,"remaining_time":0.3604797164},
{"learn":[3.422752979],"iteration":756,"passed_time":1.118236282,"remaining_time":0.3589582781},
{"learn":[3.420845924],"iteration":757,"passed_time":1.119515098,"remaining_time":0.3574177489},
{"learn":[3.418917862],"iteration":758,"passed_time":1.122530305,"remaining_time":0.3564292537},
{"learn":[3.417095735],"iteration":759,"passed_time":1.124399522,"remaining_time":0.3550735331},
{"learn":[3.414391848],"iteration":760,"passed_time":1.126915235,"remaining_time":0.3539195022},
{"learn":[3.41426711],"iteration":761,"passed_time":1.129048782,"remaining_time":0.352642533},
{"learn":[3.411976013],"iteration":762,"passed_time":1.130717484,"remaining_time":0.3512189303},
{"learn":[3.408614844],"iteration":763,"passed_time":1.134449621,"remaining_time":0.3504320818},
{"learn":[3.407906721],"iteration":764,"passed_time":1.136782537,"remaining_time":0.3492077076},
{"learn":[3.407494015],"iteration":765,"passed_time":1.139388161,"remaining_time":0.3480637464},
{"learn":[3.406287128],"iteration":766,"passed_time":1.141037055,"remaining_time":0.3466253376},
{"learn":[3.404600442],"iteration":767,"passed_time":1.142735438,"remaining_time":0.3452013301},
{"learn":[3.404012662],"iteration":768,"passed_time":1.144738517,"remaining_time":0.3438681371},
{"learn":[3.400398762],"iteration":769,"passed_time":1.146882423,"remaining_time":0.3425752692},
{"learn":[3.399737714],"iteration":770,"passed_time":1.147861655,"remaining_time":0.3409342658},
{"learn":[3.399185251],"iteration":771,"passed_time":1.157142997,"remaining_time":0.3417468954},
{"learn":[3.397245411],"iteration":772,"passed_time":1.159362097,"remaining_time":0.3404595032},
{"learn":[3.396229831],"iteration":773,"passed_time":1.162208304,"remaining_time":0.3393528123},
{"learn":[3.394002836],"iteration":774,"passed_time":1.163674931,"remaining_time":0.3378411091},
{"learn":[3.389617243],"iteration":775,"passed_time":1.16519194,"remaining_time":0.3363440653},
{"learn":[3.385426488],"iteration":776,"passed_time":1.166801448,"remaining_time":0.3348735173},
{"learn":[3.385072258],"iteration":777,"passed_time":1.169077064,"remaining_time":0.3335926842},
{"learn":[3.383842366],"iteration":778,"passed_time":1.170299119,"remaining_time":0.3320104046},
{"learn":[3.380110746],"iteration":779,"passed_time":1.17230802,"remaining_time":0.3306509801},
{"learn":[3.378595218],"iteration":780,"passed_time":1.173644904,"remaining_time":0.329101452},
{"learn":[3.377371219],"iteration":781,"passed_time":1.174837461,"remaining_time":0.3275122333},
{"learn":[3.375814782],"iteration":782,"passed_time":1.17591195,"remaining_time":0.3258913067},
{"learn":[3.374195887],"iteration":783,"passed_time":1.177474799,"remaining_time":0.3244063222},
{"learn":[3.373704309],"iteration":784,"passed_time":1.178772726,"remaining_time":0.322848581},
{"learn":[3.372971757],"iteration":785,"passed_time":1.179950829,"remaining_time":0.3212588772},
{"learn":[3.371565136],"iteration":786,"passed_time":1.181722579,"remaining_time":0.3198308886},
{"learn":[3.3700309],"iteration":787,"passed_time":1.183334235,"remaining_time":0.3183589567},
{"learn":[3.368186663],"iteration":788,"passed_time":1.185254813,"remaining_time":0.3169692846},
{"learn":[3.366710398],"iteration":789,"passed_time":1.186869472,"remaining_time":0.3154969483},
{"learn":[3.364598042],"iteration":790,"passed_time":1.188386939,"remaining_time":0.3139985718},
{"learn":[3.36348442],"iteration":791,"passed_time":1.189581521,"remaining_time":0.3124153488},
{"learn":[3.362001759],"iteration":792,"passed_time":1.191189653,"remaining_time":0.310941057},
{"learn":[3.361580401],"iteration":793,"passed_time":1.192301271,"remaining_time":0.3093376094},
{"learn":[3.359543675],"iteration":794,"passed_time":1.193324938,"remaining_time":0.30771272},
{"learn":[3.35766119],"iteration":795,"passed_time":1.194577465,"remaining_time":0.3061479936},
{"learn":[3.354592969],"iteration":796,"passed_time":1.196911065,"remaining_time":0.3048594056},
{"learn":[3.350985986],"iteration":797,"passed_time":1.198547062,"remaining_time":0.3033916123},
{"learn":[3.349589624],"iteration":798,"passed_time":1.199912653,"remaining_time":0.3018553733},
{"learn":[3.349110856],"iteration":799,"passed_time":1.201492594,"remaining_time":0.3003731484},
{"learn":[3.345315441],"iteration":800,"passed_time":1.203085449,"remaining_time":0.298893888},
{"learn":[3.34397474],"iteration":801,"passed_time":1.204145439,"remaining_time":0.2972827892},
{"learn":[3.343800902],"iteration":802,"passed_time":1.20542793,"remaining_time":0.295727649},
{"learn":[3.342329465],"iteration":803,"passed_time":1.206485403,"remaining_time":0.2941183322},
{"learn":[3.34220347],"iteration":804,"passed_time":1.207490981,"remaining_time":0.2924978153},
{"learn":[3.341279219],"iteration":805,"passed_time":1.208596449,"remaining_time":0.2909028674},
{"learn":[3.337329521],"iteration":806,"passed_time":1.210342539,"remaining_time":0.289462342},
{"learn":[3.336708453],"iteration":807,"passed_time":1.211769726,"remaining_time":0.2879452813},
{"learn":[3.333252703],"iteration":808,"passed_time":1.212940688,"remaining_time":0.2863679498},
{"learn":[3.332186769],"iteration":809,"passed_time":1.214801378,"remaining_time":0.2849534098},
{"learn":[3.330594851],"iteration":810,"passed_time":1.215857562,"remaining_time":0.2833502826},
{"learn":[3.327867442],"iteration":811,"passed_time":1.21676908,"remaining_time":0.2817150087},
{"learn":[3.327563111],"iteration":812,"passed_time":1.217771681,"remaining_time":0.2801024655},
{"learn":[3.326308994],"iteration":813,"passed_time":1.218878752,"remaining_time":0.2785152922},
{"learn":[3.326249879],"iteration":814,"passed_time":1.220163769,"remaining_time":0.2769696898},
{"learn":[3.322336238],"iteration":815,"passed_time":1.221143619,"remaining_time":0.2753559141},
{"learn":[3.320491154],"iteration":816,"passed_time":1.222191197,"remaining_time":0.2737588605},
{"learn":[3.320434271],"iteration":817,"passed_time":1.229951376,"remaining_time":0.2736566631},
{"learn":[3.319609638],"iteration":818,"passed_time":1.235439345,"remaining_time":0.2730336037},
{"learn":[3.316182682],"iteration":819,"passed_time":1.237331653,"remaining_time":0.2716093872},
{"learn":[3.313126612],"iteration":820,"passed_time":1.238516692,"remaining_time":0.2700298269},
{"learn":[3.311222803],"iteration":821,"passed_time":1.244621886,"remaining_time":0.2695166615},
{"learn":[3.309627335],"iteration":822,"passed_time":1.245816442,"remaining_time":0.2679337912},
{"learn":[3.307974895],"iteration":823,"passed_time":1.246920051,"remaining_time":0.266332438},
{"learn":[3.307321505],"iteration":824,"passed_time":1.248135807,"remaining_time":0.2647560802},
{"learn":[3.306759087],"iteration":825,"passed_time":1.249207886,"remaining_time":0.2631503296},
{"learn":[3.30484037],"iteration":826,"passed_time":1.250569583,"remaining_time":0.2616064545},
{"learn":[3.30201994],"iteration":827,"passed_time":1.251820576,"remaining_time":0.2600400229},
{"learn":[3.299302297],"iteration":828,"passed_time":1.25272864,"remaining_time":0.2584036157},
{"learn":[3.298132671],"iteration":829,"passed_time":1.253755469,"remaining_time":0.2567932888},
{"learn":[3.296976183],"iteration":830,"passed_time":1.254858069,"remaining_time":0.2551997757},
{"learn":[3.293144745],"iteration":831,"passed_time":1.257014426,"remaining_time":0.2538202206},
{"learn":[3.290284404],"iteration":832,"passed_time":1.258368368,"remaining_time":0.2522779322},
{"learn":[3.288285745],"iteration":833,"passed_time":1.260565913,"remaining_time":0.2509040066},
{"learn":[3.286662667],"iteration":834,"passed_time":1.261742749,"remaining_time":0.2493264114},
{"learn":[3.285692682],"iteration":835,"passed_time":1.262644777,"remaining_time":0.2476958653},
{"learn":[3.284565611],"iteration":836,"passed_time":1.263591028,"remaining_time":0.2460756721},
{"learn":[3.283897383],"iteration":837,"passed_time":1.264534345,"remaining_time":0.2444565202},
{"learn":[3.280712855],"iteration":838,"passed_time":1.265799233,"remaining_time":0.2429006871},
{"learn":[3.280468341],"iteration":839,"passed_time":1.266748655,"remaining_time":0.241285458},
{"learn":[3.277814895],"iteration":840,"passed_time":1.267731013,"remaining_time":0.2396780393},
{"learn":[3.276316385],"iteration":841,"passed_time":1.268712524,"remaining_time":0.2380719463},
{"learn":[3.27557063],"iteration":842,"passed_time":1.270207519,"remaining_time":0.2365629662},
{"learn":[3.27499628],"iteration":843,"passed_time":1.272893653,"remaining_time":0.2352741822},
{"learn":[3.273569958],"iteration":844,"passed_time":1.274931224,"remaining_time":0.233863124},
{"learn":[3.269665595],"iteration":845,"passed_time":1.276195703,"remaining_time":0.2323098561},
{"learn":[3.267984685],"iteration":846,"passed_time":1.277050093,"remaining_time":0.2306831928},
{"learn":[3.267702508],"iteration":847,"passed_time":1.278033188,"remaining_time":0.2290814205},
{"learn":[3.266671924],"iteration":848,"passed_time":1.279081538,"remaining_time":0.2274927117},
{"learn":[3.265359825],"iteration":849,"passed_time":1.28015492,"remaining_time":0.2259096918},
{"learn":[3.2618983],"iteration":850,"passed_time":1.281058929,"remaining_time":0.2242982144},
{"learn":[3.260456253],"iteration":851,"passed_time":1.282010431,"remaining_time":0.2226966477},
{"learn":[3.258389147],"iteration":852,"passed_time":1.282977264,"remaining_time":0.2210992471},
{"learn":[3.258108469],"iteration":853,"passed_time":1.286191676,"remaining_time":0.2198875699},
{"learn":[3.256424936],"iteration":854,"passed_time":1.287417717,"remaining_time":0.2183339987},
{"learn":[3.254817983],"iteration":855,"passed_time":1.28897278,"remaining_time":0.2168365424},
{"learn":[3.253898449],"iteration":856,"passed_time":1.290949432,"remaining_time":0.2154092985},
{"learn":[3.253023652],"iteration":857,"passed_time":1.292117412,"remaining_time":0.2138469377},
{"learn":[3.252845542],"iteration":858,"passed_time":1.293044857,"remaining_time":0.2122460125},
{"learn":[3.252316026],"iteration":859,"passed_time":1.293883755,"remaining_time":0.2106322392},
{"learn":[3.24975301],"iteration":860,"passed_time":1.294949041,"remaining_time":0.2090568138},
{"learn":[3.249151075],"iteration":861,"passed_time":1.296028115,"remaining_time":0.2074847795},
{"learn":[3.246257135],"iteration":862,"passed_time":1.296983357,"remaining_time":0.2058942293},
{"learn":[3.243826471],"iteration":863,"passed_time":1.297974167,"remaining_time":0.2043107484},
{"learn":[3.243190653],"iteration":864,"passed_time":1.300017911,"remaining_time":0.2028929688},
{"learn":[3.24008797],"iteration":865,"passed_time":1.301939961,"remaining_time":0.2014549132},
{"learn":[3.240036811],"iteration":866,"passed_time":1.30566314,"remaining_time":0.2002920388},
{"learn":[3.238676314],"iteration":867,"passed_time":1.307130564,"remaining_time":0.1987802241},
{"learn":[3.237848782],"iteration":868,"passed_time":1.308305871,"remaining_time":0.1972244753},
{"learn":[3.236405498],"iteration":869,"passed_time":1.309381766,"remaining_time":0.1956547467},
{"learn":[3.233378068],"iteration":870,"passed_time":1.310832728,"remaining_time":0.1941417014},
{"learn":[3.233169169],"iteration":871,"passed_time":1.311752167,"remaining_time":0.1925507768},
{"learn":[3.232434885],"iteration":872,"passed_time":1.312739759,"remaining_time":0.1909713052},
{"learn":[3.229978115],"iteration":873,"passed_time":1.316677327,"remaining_time":0.1898184705},
{"learn":[3.229648848],"iteration":874,"passed_time":1.318190306,"remaining_time":0.1883129009},
{"learn":[3.227208761],"iteration":875,"passed_time":1.320451706,"remaining_time":0.1869132551},
{"learn":[3.226258869],"iteration":876,"passed_time":1.321768844,"remaining_time":0.1853792107},
{"learn":[3.225331995],"iteration":877,"passed_time":1.32284026,"remaining_time":0.1838115168},
{"learn":[3.221968268],"iteration":878,"passed_time":1.324065947,"remaining_time":0.1822661884},
{"learn":[3.221166317],"iteration":879,"passed_time":1.325344187,"remaining_time":0.1807287528},
{"learn":[3.220047503],"iteration":880,"passed_time":1.326442572,"remaining_time":0.1791676119},
{"learn":[3.21982781],"iteration":881,"passed_time":1.327355194,"remaining_time":0.1775826676},
{"learn":[3.216693405],"iteration":882,"passed_time":1.328315508,"remaining_time":0.1760055656},
{"learn":[3.214798761],"iteration":883,"passed_time":1.3299021,"remaining_time":0.1745120402},
{"learn":[3.214395085],"iteration":884,"passed_time":1.331881785,"remaining_time":0.1730693845},
{"learn":[3.213470696],"iteration":885,"passed_time":1.335839659,"remaining_time":0.1718800464},
{"learn":[3.211595017],"iteration":886,"passed_time":1.336993465,"remaining_time":0.1703272396},
{"learn":[3.210965255],"iteration":887,"passed_time":1.3379206,"remaining_time":0.1687467423},
{"learn":[3.209413583],"iteration":888,"passed_time":1.338970293,"remaining_time":0.1671830174},
{"learn":[3.208331683],"iteration":889,"passed_time":1.340084223,"remaining_time":0.1656283871},
{"learn":[3.207110711],"iteration":890,"passed_time":1.341183644,"remaining_time":0.1640729711},
{"learn":[3.204519413],"iteration":891,"passed_time":1.342269813,"remaining_time":0.1625169729},
{"learn":[3.201421296],"iteration":892,"passed_time":1.343180878,"remaining_time":0.1609410459},
{"learn":[3.200691259],"iteration":893,"passed_time":1.344513318,"remaining_time":0.1594165679},
{"learn":[3.200485067],"iteration":894,"passed_time":1.346682527,"remaining_time":0.1579906875},
{"learn":[3.197467568],"iteration":895,"passed_time":1.348389572,"remaining_time":0.1565095039},
{"learn":[3.195838544],"iteration":896,"passed_time":1.349461923,"remaining_time":0.1549549365},
{"learn":[3.195671746],"iteration":897,"passed_time":1.350387698,"remaining_time":0.1533847942},
{"learn":[3.194213094],"iteration":898,"passed_time":1.35131842,"remaining_time":0.1518166412},
{"learn":[3.192884691],"iteration":899,"passed_time":1.352210185,"remaining_time":0.1502455762},
{"learn":[3.188364239],"iteration":900,"passed_time":1.353138885,"remaining_time":0.1486800773},
{"learn":[3.185219478],"iteration":901,"passed_time":1.354100179,"remaining_time":0.1471195317},
{"learn":[3.184120387],"iteration":902,"passed_time":1.355057804,"remaining_time":0.1455599191},
{"learn":[3.183725321],"iteration":903,"passed_time":1.356191766,"remaining_time":0.1440203645},
{"learn":[3.181264554],"iteration":904,"passed_time":1.35713376,"remaining_time":0.1424615549},
{"learn":[3.180741589],"iteration":905,"passed_time":1.358152421,"remaining_time":0.1409120614},
{"learn":[3.179782639],"iteration":906,"passed_time":1.359518066,"remaining_time":0.1393993166},
{"learn":[3.176377564],"iteration":907,"passed_time":1.361889065,"remaining_time":0.1379887598},
{"learn":[3.174078182],"iteration":908,"passed_time":1.36354801,"remaining_time":0.1365048063},
{"learn":[3.171242379],"iteration":909,"passed_time":1.364486821,"remaining_time":0.1349492461},
{"learn":[3.170421012],"iteration":910,"passed_time":1.365434677,"remaining_time":0.1333959234},
{"learn":[3.170087224],"iteration":911,"passed_time":1.366357777,"remaining_time":0.1318415399},
{"learn":[3.167303059],"iteration":912,"passed_time":1.367317133,"remaining_time":0.1302919941},
{"learn":[3.16705966],"iteration":913,"passed_time":1.368213486,"remaining_time":0.1287378116},
{"learn":[3.165667683],"iteration":914,"passed_time":1.369166523,"remaining_time":0.1271903328},
{"learn":[3.164689733],"iteration":915,"passed_time":1.370135041,"remaining_time":0.1256455714},
{"learn":[3.163311455],"iteration":916,"passed_time":1.37105257,"remaining_time":0.1240974518},
{"learn":[3.159425016],"iteration":917,"passed_time":1.372144481,"remaining_time":0.1225662826},
{"learn":[3.159327058],"iteration":918,"passed_time":1.373721739,"remaining_time":0.1210788475},
{"learn":[3.15819426],"iteration":919,"passed_time":1.378649316,"remaining_time":0.1198825492},
{"learn":[3.157086603],"iteration":920,"passed_time":1.379565634,"remaining_time":0.1183340772},
{"learn":[3.153354154],"iteration":921,"passed_time":1.380615468,"remaining_time":0.1167982717},
{"learn":[3.153261317],"iteration":922,"passed_time":1.381460192,"remaining_time":0.1152464082},
{"learn":[3.153168454],"iteration":923,"passed_time":1.382313988,"remaining_time":0.1136968215},
{"learn":[3.152080399],"iteration":924,"passed_time":1.38323351,"remaining_time":0.1121540684},
{"learn":[3.151635144],"iteration":925,"passed_time":1.384109274,"remaining_time":0.1106091644},
{"learn":[3.147762655],"iteration":926,"passed_time":1.385018818,"remaining_time":0.1090683643},
{"learn":[3.147172317],"iteration":927,"passed_time":1.385990116,"remaining_time":0.1075337159},
{"learn":[3.146254125],"iteration":928,"passed_time":1.386911891,"remaining_time":0.1059964954},
{"learn":[3.144869828],"iteration":929,"passed_time":1.387827982,"remaining_time":0.1044601707},
{"learn":[3.143466218],"iteration":930,"passed_time":1.389931053,"remaining_time":0.10301315},
{"learn":[3.141919643],"iteration":931,"passed_time":1.39135798,"remaining_time":0.1015153891},
{"learn":[3.141054135],"iteration":932,"passed_time":1.392868607,"remaining_time":0.1000237906},
{"learn":[3.139390417],"iteration":933,"passed_time":1.394119205,"remaining_time":0.09851377677},
{"learn":[3.139025283],"iteration":934,"passed_time":1.395235212,"remaining_time":0.09699496125},
{"learn":[3.137824183],"iteration":935,"passed_time":1.39627023,"remaining_time":0.09547146874},
{"learn":[3.135620453],"iteration":936,"passed_time":1.397656304,"remaining_time":0.09397262238},
{"learn":[3.13443178],"iteration":937,"passed_time":1.398813105,"remaining_time":0.09245886198},
{"learn":[3.132765713],"iteration":938,"passed_time":1.39979421,"remaining_time":0.09093444814},
{"learn":[3.131434124],"iteration":939,"passed_time":1.400943244,"remaining_time":0.08942190917},
{"learn":[3.128384262],"iteration":940,"passed_time":1.402092858,"remaining_time":0.08791017922},
{"learn":[3.128120455],"iteration":941,"passed_time":1.403591094,"remaining_time":0.08642068308},
{"learn":[3.126314615],"iteration":942,"passed_time":1.405795377,"remaining_time":0.08497384571},
{"learn":[3.125409666],"iteration":943,"passed_time":1.409270742,"remaining_time":0.08360080672},
{"learn":[3.123072589],"iteration":944,"passed_time":1.410499492,"remaining_time":0.08209256303},
{"learn":[3.122921099],"iteration":945,"passed_time":1.411516396,"remaining_time":0.08057281754},
{"learn":[3.122182662],"iteration":946,"passed_time":1.412569713,"remaining_time":0.0790561719},
{"learn":[3.120040951],"iteration":947,"passed_time":1.413627377,"remaining_time":0.07754074222},
{"learn":[3.118767799],"iteration":948,"passed_time":1.41479385,"remaining_time":0.07603212469},
{"learn":[3.118203218],"iteration":949,"passed_time":1.415868377,"remaining_time":0.07451938828},
{"learn":[3.116343362],"iteration":950,"passed_time":1.417110299,"remaining_time":0.07301619836},
{"learn":[3.11480829],"iteration":951,"passed_time":1.420129167,"remaining_time":0.0716031513},
{"learn":[3.112607903],"iteration":952,"passed_time":1.422626787,"remaining_time":0.07016102726},
{"learn":[3.111661241],"iteration":953,"passed_time":1.423987982,"remaining_time":0.0686618943},
{"learn":[3.110249676],"iteration":954,"passed_time":1.425103253,"remaining_time":0.0671514622},
{"learn":[3.107333579],"iteration":955,"passed_time":1.42621947,"remaining_time":0.0656419003},
{"learn":[3.107149851],"iteration":956,"passed_time":1.429133007,"remaining_time":0.06421391776},
{"learn":[3.106867336],"iteration":957,"passed_time":1.430168135,"remaining_time":0.06270048193},
{"learn":[3.10364681],"iteration":958,"passed_time":1.431476776,"remaining_time":0.06119973701},
{"learn":[3.102703811],"iteration":959,"passed_time":1.432369485,"remaining_time":0.05968206186},
{"learn":[3.101469264],"iteration":960,"passed_time":1.439451787,"remaining_time":0.05841687794},
{"learn":[3.09863569],"iteration":961,"passed_time":1.440770213,"remaining_time":0.05691192111},
{"learn":[3.09645939],"iteration":962,"passed_time":1.441796244,"remaining_time":0.05539611737},
{"learn":[3.096240186],"iteration":963,"passed_time":1.442781045,"remaining_time":0.05387979006},
{"learn":[3.094838828],"iteration":964,"passed_time":1.443955718,"remaining_time":0.0523714509},
{"learn":[3.094176802],"iteration":965,"passed_time":1.444881103,"remaining_time":0.05085502847},
{"learn":[3.093182279],"iteration":966,"passed_time":1.445673747,"remaining_time":0.04933529851},
{"learn":[3.090150687],"iteration":967,"passed_time":1.446538802,"remaining_time":0.04781946453},
{"learn":[3.088612829],"iteration":968,"passed_time":1.447546908,"remaining_time":0.04630955022},
{"learn":[3.087153684],"iteration":969,"passed_time":1.454296167,"remaining_time":0.04497823196},
{"learn":[3.085866843],"iteration":970,"passed_time":1.455827847,"remaining_time":0.04347992541},
{"learn":[3.082669094],"iteration":971,"passed_time":1.456949704,"remaining_time":0.04196974457},
{"learn":[3.081047548],"iteration":972,"passed_time":1.458047862,"remaining_time":0.0404597043},
{"learn":[3.079684322],"iteration":973,"passed_time":1.459137738,"remaining_time":0.03895028871},
{"learn":[3.07613431],"iteration":974,"passed_time":1.460130461,"remaining_time":0.03743924259},
{"learn":[3.074005935],"iteration":975,"passed_time":1.461164253,"remaining_time":0.03593026852},
{"learn":[3.072988853],"iteration":976,"passed_time":1.462215146,"remaining_time":0.03442266976},
{"learn":[3.072344268],"iteration":977,"passed_time":1.463222941,"remaining_time":0.03291503549},
{"learn":[3.070654438],"iteration":978,"passed_time":1.464613241,"remaining_time":0.03141662724},
{"learn":[3.069724506],"iteration":979,"passed_time":1.466805777,"remaining_time":0.02993481178},
{"learn":[3.067763166],"iteration":980,"passed_time":1.468286119,"remaining_time":0.02843775358},
{"learn":[3.066737893],"iteration":981,"passed_time":1.471635767,"remaining_time":0.0269749937},
{"learn":[3.065248174],"iteration":982,"passed_time":1.472689541,"remaining_time":0.02546868992},
{"learn":[3.063186837],"iteration":983,"passed_time":1.473628621,"remaining_time":0.02396144099},
{"learn":[3.062880371],"iteration":984,"passed_time":1.474878322,"remaining_time":0.02246007597},
{"learn":[3.061288645],"iteration":985,"passed_time":1.475810638,"remaining_time":0.02095471494},
{"learn":[3.059970575],"iteration":986,"passed_time":1.476697893,"remaining_time":0.01944992159},
{"learn":[3.059576341],"iteration":987,"passed_time":1.477644682,"remaining_time":0.0179471014},
{"learn":[3.058175919],"iteration":988,"passed_time":1.479349766,"remaining_time":0.01645383967},
{"learn":[3.056830702],"iteration":989,"passed_time":1.481660935,"remaining_time":0.01496627207},
{"learn":[3.056336579],"iteration":990,"passed_time":1.483182013,"remaining_time":0.01346986692},
{"learn":[3.055810414],"iteration":991,"passed_time":1.485553005,"remaining_time":0.01198026617},
{"learn":[3.055476518],"iteration":992,"passed_time":1.486792016,"remaining_time":0.01048091049},
{"learn":[3.053331734],"iteration":993,"passed_time":1.487808954,"remaining_time":0.008980738151},
{"learn":[3.050890374],"iteration":994,"passed_time":1.488687372,"remaining_time":0.007480841063},
{"learn":[3.04972623],"iteration":995,"passed_time":1.489812903,"remaining_time":0.005983184351},
{"learn":[3.047217327],"iteration":996,"passed_time":1.490767701,"remaining_time":0.004485760385},
{"learn":[3.047155483],"iteration":997,"passed_time":1.491673071,"remaining_time":0.002989324791},
{"learn":[3.04430671],"iteration":998,"passed_time":1.492626868,"remaining_time":0.001494120989},
{"learn":[3.042664195],"iteration":999,"passed_time":1.493572479,"remaining_time":0}
]}